Workbook
Name Andrew: #REF!
Name Availability: [1]B4!$D$53:$D$56
Name Bidder_and_Sub: [2]ControlSheet!$A$3:$A$13
Name csDesignMode: 1
Name CustomizationEffort: [1]B4!$D$58:$D$61
Name Department_Function: '[3]HR Process Questions'!#REF!
Name Effort: [4]Metadata!$F$2:$F$5
Name EY: #REF!
Name G1Ref: #REF!
Name G2Ref: #REF!
Name MainBidder: [2]C1!$D$7
Name ProductModules: [1]ControlSheet!$K$3:$K$56
Name ProjectRoles: [2]ControlSheet!$C$3:$C$26
Name Rank: '[5]Data Validation'!$A$1:$A$4
Name Response: [4]Metadata!$A$2:$A$6
Name review: #REF!
Name reviewers: #REF!
Name reviewers2: #REF!
Name Slicer_Domain_ID1: #N/A
Name Slicer_Domain_ID11: #N/A
Name SubsList: #REF!
Name Time0: #REF!
Name Time1: #REF!
Name Time2: #REF!
Name Value1: #REF!
Name Value2: #REF!
Name x: #REF!

Sheet Cover
C16: Saudi Air Navigation Services
C18: NDMO & NDI Questionnaire for Data Management
D20: Date: | E20: 13/11/2025 | K20: Version: | L20: 1

Sheet Priority Items
A4: Domain Name | B4: Domain ID | C4: NDI Q# | D4: Maturity Level | E4: Level No. | F4: Evidence | G4: Acceptance Criteria | H4: Priority | I4: NDMO Specifications | J4: NDI ID | K4: Meets NDMO criteria? | L4: Meets NDI Criteria? | M4: Compliance Validation Flag | N4: Comments | O4: Evidence Document Name | P4: Current Stakeholders | Q4: Order
M8: 1
M19: 1
M36: 1
M43: 1
M47: 1
A73: Data Sharing and Interoperability | B73: DSI | C73: DSI.MQ.1 | D73: Establishing | E73: 1 | F73: The Updated and Approved Results of the Initial Data Integration Assessment. | G73: The Entity must attach the report of the Data Integration assessment results, including the following, as a minimum: • The current IT Structure: an inventory of all existing IT components (data sources, systems, applications and data stores). • High Level Data Lineage including the rules according to which data is changed, and the frequency of changes. • Data Models used by the Entity's IT components. • List of all identified challenges in the Data Lineage of data movements and integration. | H73: N/A | I73: DSI.1.1 | J73: DSI.C.1.1 | K73: Under Development | L73: Partially | N73: Does not cover all requirements | O73: Integration_assessment | P73: Information Technology Data Management | Q73: 69
A74: Data Sharing and Interoperability | B74: DSI | C74: DSI.MQ.1 | D74: Defined | E74: 2 | F74: The Developed Data Integration Strategy Document. | G74: The entity must attach the developed Data Integration Strategy containing the following, at a minimum:  The Strategy’s approval by the entity’s authority holder and effective date.  The Strategy must be recent (Approved within the last three years).  The objectives, initiatives, projects and the metric indicators of the implementation of the Data Integration activities and milestones. The activities shall incorporate what is needed to achieve this Domain’s specifications, at a minimum.  The implementation roadmap of the Data Integration initiatives.  The assignment of the required resources & budget allocation to manage the implementation of this Domain. | H74: N/A | I74: N/A | J74: DSI.M.2 | K74: N/A | L74: No | P74: Information Technology Data Management | Q74: 70
A75: Data Sharing and Interoperability | B75: DSI | C75: DSI.MQ.1 | D75: Defined | E75: 2 | F75: The Developed Target Data Integration Architecture. | G75: The Entity must attach the Target Data Integration Architecture including the following, as a minimum: • The Data Integration requirements. • The Data Integration Architecture diagram. • The Architecture components. | H75: P1 | I75: DSI.1.2 | J75: DSI.C.1.2 | K75: No | L75: No | P75: Information Technology Data Management | Q75: 71
A76: Data Sharing and Interoperability | B76: DSI | C76: DSI.MQ.1 | D76: Defined | E76: 2 | F76: The Developed Data Integration Plan (Including Data Sharing Activities). | G76: The Entity must attach the developed Data Integration Plan including the following, as a minimum: • The summarized Architecture briefs. • The roadmap and covenant charters of the projects and initiatives in the plan. • The assignment of the required resources & budget allocation for the projects and initiatives in the plan. | H76: P1 | I76: DSI.1.3 | J76: DSI.C.1.3 | K76: Under Development | L76: Partially | N76: Roadmap needs to be updated to include summarized architecture briefs | O76: SANS-CYB-DM-PL-02-SANS-Data Strategic Requirements and Data- Ver.1.0 Mar 2024 | P76: Information Technology Data Management | Q76: 72
M85: 1
M87: 1
M88: 1
M89: 1
M94: 1
M95: 1
M97: 1
A101: Data Sharing and Interoperability | B101: DSI | C101: DSI.MQ.3 | D101: Defined | E101: 2 | F101: The Integration Requirements Document. | G101: The Entity must attach the Integration / Interoperability Requirements document containing the following, as a minimum: • A clearly defined scope. • Entity's Business goals / objectives and aims to be achieved. • Implementation Timeline. • Resources required. • Cost estimate. • Functional requirements. • Non-Functional requirements. | H101: P1 | I101: DSI.3.1 | J101: DSI.C.3.1 | K101: Yes | L101: Yes | O101: ICD_Diplomatic Clearance System (DCS) (DSI.MQ.3), SANS-RAC-ICD-AODB-FDS V0.1- 05 Nov 2023 (DSI.MQ.3) | P101: Information Technology Data Management | Q101: 97
A102: Data Sharing and Interoperability | B102: DSI | C102: DSI.MQ.3 | D102: Defined | E102: 2 | F102: The Solution Design Document. | G102: The Entity must attach the Solution Design document including the following, as a minimum: • Integration Solution Overview. • Target Data Integration Architecture. • Data Orchestration – The Data Flow Diagram (DFD). • Source to Target Mapping – A set of Data Transformation instructions that determine how to convert the structure and content of Data in the source system to the structure and content needed in the target system. The instructions shall include the following, as a minimum: ◦ The technical format of Data at the source and the target. ◦ The Specifications of transformations required for all intermediate staging points between the source and the target. | H102: P1 | I102: DSI.3.2 | J102: DSI.C.3.2 | K102: No | L102: No | N102: The provided evidence does not align with NDI requirements. (e.g. source to target mapping, data flows.are missing) | O102: ICD_Diplomatic Clearance System (DCS) (DSI.MQ.3), SANS-RAC-ICD-AODB-FDS V0.1- 05 Nov 2023 (DSI.MQ.3) | P102: Information Technology Data Management | Q102: 98
M105: 1
A109: Data Sharing and Interoperability | B109: DSI | C109: DSI.MQ.4 | D109: Establishing | E109: 1 | F109: The Existing Data Integration or Data Movement Processes within the Entity. | G109: The Entity must attach a report on the current Data Integration / Interoperability Processes or the current Data Movement Processes within the Entity. | H109: N/A | I109: N/A | J109: DSI.M.20 | K109: N/A | L109: Yes | O109: Integration_assessment, SANS Data Achitecture Assessment v1.0 | P109: Information Technology Data Management | Q109: 105
A110: Data Sharing and Interoperability | B110: DSI | C110: DSI.MQ.4 | D110: Defined | E110: 2 | F110: The Developed Data Migration Processes (i.e.: ETL). | G110: The Entity must attach a report on the Processes and Standards process to integrate data from disparate sources and load it into the Data Warehouse Store i.e.: Extract, Transform, Load (ETL). | H110: P2 | I110: DSI.4.1 | J110: DSI.C.4.1.1 | K110: No | L110: No | M110: 1 | N110: The provided document is a data sharing request letter. It is not relevant to the evidence required here. | O110: GACA Forecast Data Request - Letter (DSI.MQ.4) | P110: Information Technology Data Management | Q110: 106
A111: Data Sharing and Interoperability | B111: DSI | C111: DSI.MQ.4 | D111: Defined | E111: 2 | F111: The Developed Data Migration Processes (i.e.: ELT). | G111: The Entity must attach a report on the Processes and Standards process to store the unstructured data in its raw native format in the Data Lake i.e.: Extract, Load, Transform (ELT). | H111: P2 | I111: DSI.4.2 | J111: DSI.C.4.2.1 | K111: No | L111: No | M111: 1 | P111: Information Technology Data Management | Q111: 107
A113: Data Sharing and Interoperability | B113: DSI | C113: DSI.MQ.4 | D113: Defined | E113: 2 | F113: The Defined Data Sharing Controls. | G113: The Entity must attach a report on the Controls that have been identified and defined for Data Sharing. | H113: N/A | I113: N/A | J113: DSI.M.22 | K113: N/A | L113: No | P113: Data Governance & Protection Information Technology Data Management | Q113: 109
M115: 1
M116: 1
A119: Data Quality | B119: DQ | C119: DQ.MQ.1 | D119: Establishing | E119: 1 | F119: Evidence of the Existing Data Quality (DQ) Related Activities. | G119: The Entity must attach a report on the activities that are practiced in the DQ Domain. For each activity, the report must contain the following, as a minimum: • Copies / screenshots of e-mail correspondences which support practicing the activity. • Copies / screenshots of documents which support practicing the activity. • Screenshots of the systems which support practicing the activity. | H119: N/A | I119: N/A | J119: DQ.M.1 | K119: N/A | L119: Yes | O119: DQ.MQ.1-3 ticket1, DQ.MQ.1-3 ticket1_1 | P119: Safety Quality & Compliance Data Management | Q119: 115
A120: Data Quality | B120: DQ | C120: DQ.MQ.1 | D120: Defined | E120: 2 | F120: The Defined and Approved DQ Implementation Plan. | G120: The Entity must attach a defined and approved DQ management plan to implement and manage the activities which aim at improving the Entity’s Data. This plan must contain the following, as a minimum: • A roadmap that includes the activities and milestones of implementing the DQ Management practices in the Entity. The activities shall incorporate what is needed to achieve this Domain’s specifications, as a minimum. • The assignment of the required resources & budget allocation to manage the implementation of the DQ Management Plan. | H120: P1 | I120: DQ.1.2 | J120: DQ.C.1.2 | K120: Yes | L120: Yes | O120: SANS-CYB-DM-PL-01-SANS-Data Strategy Roadmap & Investment Plan- Ver.1.0 Mar 2024, Page # 56 | P120: Data Governance & Protection Safety Quality & Compliance Data Management | Q120: 116
A126: Data Quality | B126: DQ | C126: DQ.MQ.2 | D126: Establishing | E126: 1 | F126: The Existing DQ Domain Initiatives. | G126: The Entity must attach a report on the current DQ Domain initiatives. | H126: N/A | I126: N/A | J126: DQ.M.7 | K126: N/A | L126: Yes | O126: SANS-CYB-DM-PL-01-SANS-Data Strategy Roadmap & Investment Plan- Ver.1.0 Mar 2024, Page # 56 | P126: Safety Quality & Compliance Data Management | Q126: 122
A127: Data Quality | B127: DQ | C127: DQ.MQ.2 | D127: Establishing | E127: 1 | F127: The Existing Processes for Detecting DQ Issues. | G127: The Entity must attach a report on the current DQ issue detection processes. | H127: N/A | I127: N/A | J127: DQ.M.8 | K127: N/A | L127: No | N127: The evidence provided lacks the required information on DQ issue detection and correction processes. | O127: DQ.MQ.1-3 ticket1 DQ.MQ.1-3 ticket1_1 | P127: Safety Quality & Compliance Data Management | Q127: 123
A128: Data Quality | B128: DQ | C128: DQ.MQ.2 | D128: Establishing | E128: 1 | F128: The Existing Processes Used for Data Corrections or Data Validations. | G128: The Entity must attach a report on the current processes used for Data corrections or Data validations. | H128: N/A | I128: N/A | J128: DQ.M.9 | K128: N/A | L128: No | N128: The evidence provided lacks the required information on DQ issue detection and correction processes. | O128: DQ.MQ.1-3 ticket1 DQ.MQ.1-3 ticket1_1 | P128: Safety Quality & Compliance Data Management | Q128: 124
A129: Data Quality | B129: DQ | C129: DQ.MQ.2 | D129: Defined | E129: 2 | F129: The Prioritized List of Data Elements. | G129: The Entity must attach a report listing the Data elements ranked / prioritized based on business requirements. The first priority Data must include the Entity’s Master Data, as a minimum. | H129: P1 | I129: DQ.1.1 | J129: DQ.C.1.1 | K129: No | L129: No | P129: Safety Quality & Compliance Data Management | Q129: 125
A130: Data Quality | B130: DQ | C130: DQ.MQ.2 | D130: Defined | E130: 2 | F130: The Defined DQ Dimensions for the Entity's Datasets. | G130: The Entity must attach a report clarifying the defined DQ Dimensions for the Entity's Datasets including the following, as a minimum: • Completeness (The degree of how complete data records are). • Uniqueness (The degree of how unique data records are without duplicates). • Timeliness (The degree to which data is up to date and available when it is needed). • Validity (The degree of records' conformance to the established formats, types and ranges). • Accuracy (The degree to which data values align to real values). • Consistency (The degree to which data is consistent across the Entity’s business and across different sources). | H130: P2 | I130: DQ.2.1 | J130: DQ.C.2.1 | K130: No | L130: No | P130: Safety Quality & Compliance Data Management | Q130: 126
A131: Data Quality | B131: DQ | C131: DQ.MQ.2 | D131: Defined | E131: 2 | F131: The Data Quality Rules Report. | G131: The Entity must attach a report clarifying the list of defined DQ Rules that are aligned with the DQ Dimensions including the following, as a minimum: • The DQ rule owner. • The business description of the requirement to be validated by the rule. • Regarding the particular data whose quality is being measured: The assignment of Rules to each of the DQ Dimensions including the following, as a minimum: ◦ Completeness. ◦ Uniqueness. ◦ Timeliness. ◦ Validity. ◦ Accuracy. ◦ Consistency. • The list of Data Attributes validated by the defined rules. • The metrics that are calculated when validating each DQ rule. • The escalation threshold that triggers a DQ alert for the rule. | H131: P2 | I131: DQ.2.2 | J131: DQ.C.2.1.2 | K131: No | L131: No | M131: 1 | P131: Safety Quality & Compliance Data Management | Q131: 127
A132: Data Quality | B132: DQ | C132: DQ.MQ.2 | D132: Defined | E132: 2 | F132: The Developed & Approved Processes for DQ Issue Management & Remediation. | G132: The Entity must attach a report clarifying the Developed & Approved Processes for DQ Issue Management & Remediation followed for DQ issue management & remediation / resolution including, as a minimum, the following: • The development of a remediation plan. The remediation plan must include the following, as a minimum: • A "Root Cause" analysis to determine the causes of the identified DQ issue. • An Impact analysis to assess the negative consequences and determine an issue level (whether it is local / limited, or at the Entity level). • The definition & identification of the DQ Targets set for each of the issues & challenges, related to each DQ Dimension, depending on the context of the issue / challenge within the Entity. • The definition & identification of the options for resolving the issue's "Root Cause", including a feasibility analysis. • The specifications of the Data Cleansing process to be performed if the solution does not correct the "Root Cause" of the DQ issue. • The decision & the logical rationale for selecting the specific option (chosen) to solve the issue. • The implementation status of the issue's most suitable resolution choice (including any change). • The review of the implemented resolution and a verification that the issue is resolved. • Establishing & developing a roadmap and milestones for the resolution of the noticed & identified DQ issues. • Allocating the necessary resources to implement the DQ issue identification plan. | H132: P2 | I132: DQ.2.3 | J132: DQ.C.2.3.1 | K132: Under Development | L132: Partially | M132: 1 | N132: Data quality activities are conducted reactively, lacking formalized data quality practices and standards | P132: Safety Quality & Compliance Data Management | Q132: 128
A133: Data Quality | B133: DQ | C133: DQ.MQ.2 | D133: Activated | E133: 3 | F133: The Planned & Conducted Initial & Periodic Data Quality Assessment Report. | G133: The Entity must attach a report clarifying the initial & periodic DQ assessment, which was planned for and conducted (already). The assessment must include the following, as a minimum: • Collecting business requirements for the Quality of Data in the scope. • Establishing & defining DQ Rules based on the collected business requirements specifically. • Performing a check by Data Profiling based on the Predefined DQ Rules. • Reporting the discovered and identified DQ comments & issues to the concerned / relevant department in the Entity. • Developing plans (with key milestones) for resolving the discovered & identified DQ issues. | H133: P1 | I133: DQ.1.3 | J133: DQ.C.1.3 | K133: No | L133: No | P133: Safety Quality & Compliance Data Management | Q133: 129
M134: 1
A144: Data Quality | B144: DQ | C144: DQ.MQ.3 | D144: Establishing | E144: 1 | F144: The Existing DQ Monitoring Practices. | G144: The Entity must attach an updated & approved report clarifying the Entity’s current DQ monitoring practices. | H144: N/A | I144: N/A | J144: DQ.M.16 | K144: N/A | L144: No | N144: DQ.MQ.1-3 ticket1, DQ.MQ.1-3 ticket1_1 | O144: The evidence provided lacks information on the current Data Quality monitoring practices (i.e., number of issues detected, validated, resolved and the status of open DQ issues) | P144: Safety Quality & Compliance Data Management | Q144: 140
A145: Data Quality | B145: DQ | C145: DQ.MQ.3 | D145: Establishing | E145: 1 | F145: Evidence of the Entity's Current DQ Status. | G145: The Entity must attach an updated & approved report showing the current DQ situation. | H145: N/A | I145: N/A | J145: DQ.M.17 | K145: N/A | L145: No | N145: DQ.MQ.1-3 ticket1, DQ.MQ.1-3 ticket1_1 | O145: The evidence provided lacks information on the current Data Quality monitoring practices (i.e., number of issues detected, validated, resolved and the status of open DQ issues) | P145: Safety Quality & Compliance Data Management | Q145: 141
A146: Data Quality | B146: DQ | C146: DQ.MQ.3 | D146: Defined | E146: 2 | F146: The Defined and Formalized DQ Monitoring Plan. | G146: The Entity must attach the defined DQ monitoring plan showing activities required to monitor and document the data quality status on a regular with the assigned resources for implementation. | H146: P2 | I146: DQ.2.2 | J146: DQ.C.2.2.1 | K146: No | L146: No | M146: 1 | P146: Safety Quality & Compliance Data Management | Q146: 142
A147: Data Quality | B147: DQ | C147: DQ.MQ.3 | D147: Defined | E147: 2 | F147: The Defined DQ Checkpoints Report. | G147: The Entity must attach a report clarifying specific Checkpoints defined for DQ Monitoring. | H147: N/A | I147: N/A | J147: DQ.M.18 | K147: N/A | L147: No | P147: Safety Quality & Compliance Data Management | Q147: 143
M148: 1
A154: Data Quality | B154: DQ | C154: DQ.MQ.4 | D154: Establishing | E154: 1 | F154: The Existing List of Data Standards and Data Definitions. | G154: The Entity must attach an updated & approved report listing the current DQ standards and explaining the Data definitions. | H154: N/A | I154: N/A | J154: DQ.M.20 | K154: N/A | L154: No | P154: Safety Quality & Compliance Data Management | Q154: 150
A155: Data Quality | B155: DQ | C155: DQ.MQ.4 | D155: Defined | E155: 2 | F155: The Developed Data Standards for Data Elements. | G155: The Entity must attach an updated & approved report clarifying the Standards developed for the Data Elements. | H155: N/A | I155: N/A | J155: DQ.M.21 | K155: N/A | L155: No | P155: Safety Quality & Compliance Data Management | Q155: 151
A156: Data Quality | B156: DQ | C156: DQ.MQ.4 | D156: Defined | E156: 2 | F156: The Identified Metadata with their Definitions. | G156: The Entity must attach an updated & approved report clarifying the identified Metadata with their definitions. | H156: N/A | I156: N/A | J156: DQ.M.22 | K156: N/A | L156: No | P156: Safety Quality & Compliance Data Management | Q156: 152
A157: Data Quality | B157: DQ | C157: DQ.MQ.4 | D157: Defined | E157: 2 | F157: The Identified Datasets to be Published on the National Data Catalog (NDC). | G157: The Entity must attach an updated & approved report showing the identified datasets to be published on the National Data Catalog (NDC). | H157: N/A | I157: N/A | J157: DQ.M.23 | K157: N/A | L157: No | N157: Could be no relevant to SANS | P157: Safety Quality & Compliance Data Management | Q157: 153
M174: 1
M175: 1
M176: 1
M180: 1
A186: Data Value Realization | B186: DVR | C186: DVR.MQ.1 | D186: Establishing | E186: 1 | F186: The Existing List of Data Value Realization (DVR) Activities. | G186: A document must be attached covering a Proof-of-Concept (POC), or other temporary tasks performed as practices that support Data Value & Benefit Realization within the Entity. The document must include the following: • The currently existing DVR Domain practices. • A separate description for each activity including, as a minimum: ◦ The name of the activity. ◦ The purpose of the activity. ◦ The achieved or expected output of the activity. | H186: N/A | I186: N/A | J186: DVR.M.1 | K186: N/A | L186: No | P186: Data Management | Q186: 182
A187: Data Value Realization | B187: DVR | C187: DVR.MQ.1 | D187: Defined | E187: 2 | F187: The Data Value Realization (DVR) plan. | G187: A recent and authorized Data Value Realization Plan, approved by the relevant authority, must be attached to activate the potential for generating revenue from data (profit-driven data revenue) and to enable data-driven cost reduction initiatives. The plan must include, at a minimum, the following: • A roadmap outlining the activities and milestone objectives for Data Value Realization Use Cases. The activities must include, at a minimum, the necessary steps to meet the specifications of this domain. • Allocation of the required resources and budget for managing the implementation of Data Value Realization Use Cases. | H187: P1 | I187: DVR.1.2 | J187: DVR.C.1.2 | K187: Yes | L187: Yes | O187: SANS-CYB-DM-PL-01-SANS-Data Strategy Roadmap & Investment Plan- Ver.1.0 Mar 2024, Page #69 | P187: Data Governance & Protection Data Management | Q187: 183
A188: Data Value Realization | B188: DVR | C188: DVR.MQ.1 | D188: Defined | E188: 2 | F188: The List of Identified Use Cases for Both Revenue Generation & Cost Optimization. | G188: A document must be attached covering the DVR use cases. Each use case should be documented with the following details, as a minimum: • Name of use case. • Type of use case e.g.: 1- Data Revenue Generation Use Cases – Data or Data Products which generate revenue for the Entity. 2- Cost Saving Use Cases – Data related cases which will directly or indirectly contribute to reducing expenses and achieving greater efficiency. • The stakeholders required to implement the use cases, the official who will lead the use case, and the target beneficiary who will benefit from the implementation of the use case. • A list of business requirements needed to implement the use cases. • Data sources and required data fields. • The technology required to implement the use cases. | H188: P1 | I188: DVR.1.1 | J188: DVR.C.1.1.1 | K188: No | L188: No | M188: 1 | P188: Data Management | Q188: 184
A189: Data Value Realization | B189: DVR | C189: DVR.MQ.1 | D189: Defined | E189: 2 | F189: A Document Explaining the Payback Period and Return on Investment (ROI) for Each Identified Use Case. | G189: A document must be attached containing an estimation of the payback period and the ROI for each DVR use case. | H189: P1 | I189: DVR.1.1 | J189: DVR.C.1.1.2 | K189: No | L189: No | M189: 1 | P189: Data Management | Q189: 185
M193: 1
A198: Data Value Realization | B198: DVR | C198: DVR.MQ.2 | D198: Establishing | E198: 1 | F198: The Existing Practices Related to Supporting the Data Revenue Generation Process. | G198: A document must be attached containing the current practices which support Data revenue generation including a list of the current activities (reports and/or dashboards...etc.) related to the DVR Domain practices. | H198: N/A | I198: N/A | J198: DVR.M.8 | K198: N/A | L198: No | P198: Data Governance & Protection | Q198: 194
A199: Data Value Realization | B199: DVR | C199: DVR.MQ.2 | D199: Defined | E199: 2 | F199: The Defined Pricing Scheme. | G199: A document must be attached containing an appropriate Pricing Model for any Data and for any Data Product that’s expected to generate revenue. | H199: P2 | I199: DVR.2.1 | J199: DVR.C.2.1 | K199: No | L199: No | P199: Data Governance & Protection | Q199: 195
A200: Data Value Realization | B200: DVR | C200: DVR.MQ.2 | D200: Defined | E200: 2 | F200: The Data or Data Product Price Calculation. | G200: A document must be attached containing the total expense calculation for each Data or Data Product which is expected to generate revenue. The total cost shall include the following as a minimum: • The Data Collection Cost – The total of the costs incurred for collecting, cleansing, and curating data. • The Data Development Cost – The total of the costs incurred for developing analytical models, Data visualizations and other valueadded services provided on top of the collected data. | H200: P2 | I200: DVR.2.2 | J200: DVR.C.2.2 | K200: No | L200: No | P200: Data Governance & Protection | Q200: 196
A201: Data Value Realization | B201: DVR | C201: DVR.MQ.2 | D201: Defined | E201: 2 | F201: The Adopted / Approved Charging Model for Each Data or Data Product. | G201: A document must be attached containing the approved Charging Calculation Model for each Data or Data Product that’s expected to generate revenue. " Here are examples of Charging Calculation Models, but not limited to: • The Subscription Model. • The Consumption Based Model. • The Freemium / Premium Model. • The One Time Fee Model." The fee calculation model(s) must be approved by the authorized person within the entity and must be valid/effective. | H201: P2 | I201: DVR.2.3 | J201: DVR.C.2.3 | K201: No | L201: No | P201: Data Governance & Protection | Q201: 197
M203: 1
M209: 1
M210: 1
M222: 1
M223: 1
A224: Document and Content Management | B224: DCM | C224: DCM.MQ.2 | D224: Defined | E224: 2 | F224: The Developed DCM Metadata Publishing Procedures. | G224: The Entity must attach reports containing the documentations of the developed processes for the following: • Publishing the Metadata of Documents & Contents. • Classifying Documents & Contents. | H224: N/A | I224: N/A | J224: DCM.M.10 | K224: N/A | L224: No | P224: Safety Quality & Compliance Data Management | Q224: 220
M225: 1
M226: 1
A244: Data Operations | B244: DO | C244: DO.MQ.1 | D244: Defined | E244: 2 | F244: The Periodic Forecasting Plan for Storage Capacity. | G244: The Entity must attach a periodic forecast report on proactive planning to satisfy the expected storage capacity requirements, including the following, as a minimum: • Previous (historical) Data storage capacities used. • Performance Evaluation of the Entity’s applications and needs. • A list of upcoming applications to be developed and built for the Entity. | H244: P2 | I244: DO.1.2 | J244: DO.C.1.2.1 | K244: No | L244: No | M244: 1 | P244: Information Technology | Q244: 240
A245: Data Operations | B245: DO | C245: DO.MQ.1 | D245: Defined | E245: 2 | F245: The Database Technology Evaluation Process and Selection Criteria. | G245: The Entity must attach the Database Technology Evaluation Process and Selection Criteria including the following, as a minimum: • The Total Cost of Ownership (TCO) including, at least: licensing, support, training, and hardware. • The availability of resources skilled in these technological solutions, both internally and in the job market. • The presence of software tools related to the Database technologies being evaluated in the Entity. • Volume and velocity limits of the utilized technologies. • Reliability provided by the utilized technologies. • Scalability of each technology. • Security controls provided by the utilized technologies. | H245: P2 | I245: DO.1.4 | J245: DO.C.1.4.1 | K245: No | L245: No | M245: 1 | P245: Information Technology | Q245: 241
M247: 1
M248: 1
A255: Data Operations | B255: DO | C255: DO.MQ.2 | D255: Establishing | E255: 1 | F255: Evidences of Data Operations Done within the Entity. | G255: The Entity must attach evidences of the Database operations performed by the Entity (e.g. e-mails, screenshots). | H255: N/A | I255: N/A | J255: DO.M.8 | K255: N/A | L255: Yes | O255: DO.MQ.2 Database Management Activities F&I1 | P255: Information Technology | Q255: 251
A256: Data Operations | B256: DO | C256: DO.MQ.2 | D256: Defined | E256: 2 | F256: The Process Documentation of the Detailed Practices of Data Operations, (A. Database Monitoring). | G256: The Entity must attach the overall Process of the Detailed Practices of Database Monitoring, including the following, as a minimum: • The process for monitoring and reporting database performance on regular basis. | H256: P2 | I256: DO.3.1 | J256: DO.C.3.1.1 | K256: No | L256: No | M256: 1 | N256: There is currently no formal report or documented procedure that defines the monitoring frequency or provides a step by step description of the monitoring process for active systems. A comprehensive monitoring report and formalized process documentation must be developed to ensure full compliance with NDI requirements. | O256: DO.MQ.2 Database Management Activities F&I1 | P256: Information Technology | Q256: 252
A257: Data Operations | B257: DO | C257: DO.MQ.2 | D257: Defined | E257: 2 | F257: B. Database Access Control. | G257: The Entity must attach the Detailed process for providing the Entity's employees access to the databases. | H257: P2 | I257: DO.3.2 | J257: DO.C.3.2 | K257: No | L257: No | P257: Information Technology | Q257: 253
A258: Data Operations | B258: DO | C258: DO.MQ.2 | D258: Defined | E258: 2 | F258: C. Storage Configuration Management. | G258: The entity must attach the detailed Practices of Storage Configuration Management including at a minimum: • Configuration identification. • Configuration change control. • Configuration status accounting. • Configuration audits. | H258: P2 | I258: DO.3.3 | J258: DO.C.3.3 | K258: No | L258: No | P258: Information Technology | Q258: 254
A259: Data Operations | B259: DO | C259: DO.MQ.2 | D259: Defined | E259: 2 | F259: D. DBMS Versioning Mechanism. | G259: The Entity must attach the overall Process of the Detailed Practices of DBMS Versioning / Updating Mechanism Covering: • The Management Plan of Updated Releases / Versions. • The Strategy Including Analysis and Rationale. | H259: P3 | I259: DO.3.4 | J259: DO.C.3.4 | K259: No | L259: No | P259: Information Technology | Q259: 255
A260: Data Operations | B260: DO | C260: DO.MQ.2 | D260: Defined | E260: 2 | F260: E. The Database Performance Service Level Agreements and Operational Level Agreements (SLAs & OLAs). | G260: The Entity must attach the process for defining Database Performance Service Level Agreements and Operational Level Agreements (SLAs & OLAs). | H260: N/A | I260: N/A | J260: DO.M.9 | K260: N/A | L260: No | P260: Information Technology | Q260: 256
M261: 1
A267: Data Operations | B267: DO | C267: DO.MQ.3 | D267: Establishing | E267: 1 | F267: Evidences of Data Storage Backup Instruction Documents. | G267: The Entity must attach a sample document of the Data storage backup instructions (e.g. e-mail, guide / manual). | H267: N/A | I267: N/A | J267: DO.M.14 | K267: N/A | L267: Yes | O267: SANS- IT - POL - 01-IT Change Management - Ver.1.0-Nov 2024 (DO.MQ.3), DO.MQ.3 | P267: Information Technology | Q267: 263
A268: Data Operations | B268: DO | C268: DO.MQ.3 | D268: Defined | E268: 2 | F268: The Developed Processes and Practices for Data Storage Backups and Recovery. | G268: The Entity must attach the process and practices developed for the "Data Storage Backup" and "Data Backup Recovery", including the following, as a minimum: • Defining and determining the backup frequency of each information system. • Scope of backup for each information system including the scope of Data and the scope of Database transaction logs. • Location of backup files including a storage medium and a physical location. • Periodic validations of backup completions using system copies in non-production environments. | H268: P2 | I268: DO.4.1 | J268: DO.C.4.1 | K268: No | L268: No | P268: Information Technology | Q268: 264
A269: Data Operations | B269: DO | C269: DO.MQ.3 | D269: Defined | E269: 2 | F269: The Business Continuity Plan (BCP) and Processes. | G269: The Entity must attach the processes and Business Continuity Plan (BCP), which include at a minimum, the following: • Risk assessment and business impact analysis. • Functional roles and responsibilities. • Alternative work locations. • The infrastructure. • Incident management. • The communication mechanisms of the continuity procedures to notify the relevant stakeholders, e.g.: Employees and customers • Periodic training courses with scenario-based trial simulations to evaluate the response and identify areas for improvement. | H269: N/A | I269: N/A | J269: DO.M.15 | K269: N/A | L269: No | N269: The provided evidence is IT change management policy. It lacks information on the BCP processes and plan. | P269: Information Technology | Q269: 265
A270: Data Operations | B270: DO | C270: DO.MQ.3 | D270: Defined | E270: 2 | F270: The Disaster Recovery (DR) Plan and the Processes. | G270: The Entity must attach • Disaster Recovery (DR) Processes and Plan including, as a minimum: • A prioritized list of information systems defining their recovery order. • Assigning the roles responsible for addressing / handling incident cases and responding. • Defining and specifying the procedural actions to be taken to activate a response to each incident through the system. • Defining and specifying the procedural actions to be taken to reduce the damage and mitigate the incident consequences on the Entity's critical operations. • Definition & identification of Recovery Point Objectives (RPO) (A maximum targeted period within which Data might be lost without causing damage to the business) for each information system covered in the plan. • Definition of Recovery Time Objectives (RTO) (A maximum targeted duration of time within which the Database can be down without causing damage to the business) for each information system covered in the plan. • Definition of Recovery activities. • Periodic training courses with scenario-based trial simulations to evaluate the response and identify areas for improvement. | H270: P2 | I270: DO.4.2 | J270: DO.C.4.2 | K270: No | L270: No | P270: Information Technology | Q270: 266
A271: Data Operations | B271: DO | C271: DO.MQ.3 | D271: Defined | E271: 2 | F271: A Document of Actions Required to Implement Database Changes and Rollbacks. | G271: The Entity must attach a document explaining the definitions of the measures and the procedural action steps to be taken to implement the changes on each Database or to rollback / undo the changes as & when needed. | H271: N/A | I271: N/A | J271: DO.M.16 | K271: N/A | L271: No | P271: Information Technology | Q271: 267
A279: Data Catalog and Metadata | B279: MCM | C279: MCM.MQ.1 | D279: Establishing | E279: 1 | F279: The Recorded or Documented Metadata Report. | G279: The Entity must attach a report on the Metadata recorded or documented as part of any project’s implementation, or in standalone applications. | H279: N/A | I279: N/A | J279: MCM.M.1 | K279: N/A | L279: No | P279: Data Management | Q279: 275
A280: Data Catalog and Metadata | B280: MCM | C280: MCM.MQ.1 | D280: Defined | E280: 2 | F280: The Approved Metadata and Data Catalog Plan. | G280: The Entity must attach the approved MCM tool / solution implementation plan including the following, as a minimum: • A roadmap that includes the projects and milestones of the technological tool / solution implementation for the Data Catalog. The activities shall incorporate what is needed to achieve this Domain’s specifications, as a minimum. • The assignment of the required resources & budget allocation to manage the implementation of the Data Catalog Automation tool. | H280: P1 | I280: MCM.1.1 | J280: MCM.C.1.1 | K280: Yes | L280: Yes | O280: SANS-CYB-DM-PL-01-SANS-Data Strategy Roadmap & Investment Plan- Ver.1.0 Mar 2024, Pg. #48 | P280: Data Management | Q280: 276
A281: Data Catalog and Metadata | B281: MCM | C281: MCM.MQ.1 | D281: Defined | E281: 2 | F281: The Approved Metadata Structure. | G281: The Entity must attach an updated and approved report illustrating the approved Metadata architecture and Metadata framework. The report must include the following, as a minimum: • The Business Metadata fields to be filled in the Data Catalog. • The additional fields based on the Entity’s requirements and any other regulatory requirements must be documented in the Data Catalog. | H281: P1 | I281: MCM.4.3 | J281: MCM.C.4.3 | K281: No | L281: No | P281: Data Management | Q281: 277
A286: Data Catalog and Metadata | B286: MCM | C286: MCM.MQ.2 | D286: Establishing | E286: 1 | F286: Evidences of Current Existing Metadata. | G286: The Entity must attach a report proving the existence of the identified Metadata within standalone applications or for a specific project. | H286: N/A | I286: N/A | J286: MCM.M.6 | K286: N/A | L286: No | P286: Data Management | Q286: 282
A287: Data Catalog and Metadata | B287: MCM | C287: MCM.MQ.2 | D287: Defined | E287: 2 | F287: The Selected Data Catalog Tool. | G287: The Entity must attach an approved report clarifying the technology / tool chosen for the Data Catalog (The information includes: The Vendor, version, and specifications). | H287: N/A | I287: N/A | J287: MCM.M.7 | K287: N/A | L287: No | P287: Data Management | Q287: 283
A288: Data Catalog and Metadata | B288: MCM | C288: MCM.MQ.2 | D288: Defined | E288: 2 | F288: The Approved and Prioritized Data Sources Report. | G288: The Entity must attach an approved report that includes the following, as a minimum: • The Data Catalog Sources where each Source has an approved priority. • The definitions of the Entity’s business Metadata and the technical Metadata. | H288: P1 | I288: MCM.1.2 | J288: MCM.C.1.2 | K288: No | L288: No | P288: Data Management | Q288: 284
A289: Data Catalog and Metadata | B289: MCM | C289: MCM.MQ.2 | D289: Defined | E289: 2 | F289: The Developed and Approved Target Metadata Architecture. | G289: The Entity must attach an approved report clarifying the developed and approved target Metadata architecture including (but not limited to), the following: • Metadata Sources -the Entity's Data Sources that are sources of Metadata used in the Data Catalog. • Metadata Repository - the Data Catalog as the Entity's central Metadata Repository. • Metadata Flows - A definition of Metadata Flow between the Metadata Sources and the Metadata Repository. • Metadata Model - A Metadata Model used by the Entity's Data Catalog. | H289: P1 | I289: MCM.1.3 | J289: MCM.C.1.3 | K289: No | L289: No | P289: Data Management | Q289: 285
A290: Data Catalog and Metadata | B290: MCM | C290: MCM.MQ.2 | D290: Defined | E290: 2 | F290: The Data Catalog Tool Implementation Requirements Report. | G290: The Entity must attach an approved report clarifying the Data Catalog tool implementation requirements, including the following, as a minimum: • The procurement approval for a tool to automate the Data Catalog. • The approved plan to implement the Data Catalog automation tool. | H290: N/A | I290: N/A | J290: MCM.M.8 | K290: N/A | L290: No | P290: Data Management | Q290: 286
A291: Data Catalog and Metadata | B291: MCM | C291: MCM.MQ.2 | D291: Defined | E291: 2 | F291: The Approved and Developed Data Catalog Training Plan. | G291: The entity must attach the recent and developed training and awareness plan approved by the entity’s authority holder regarding the Data Catalog usages, including the following, at a minimum: • The training and awareness plan’s approval and validity / expiry dates. • The training and awareness programs plan implementation dates. • The scope of the training and awareness. • The objectives of the training and awareness. • The training shall include the following: ◦ An overview of the Data Catalog concept and benefits. ◦ Introductory and advanced lessons on the Automated Data Catalog Tool and its functionalities. ◦ Practical (Hands on) exercises based on use cases on the automated Data Catalog tool. ◦ The training and awareness target audiences. ◦ The topics of the training programs and awareness campaigns. ◦ The methods and channels through which the Training plan will be conducted. ◦ Identifying the MCM Domain Awareness campaign channels, which include: ◦ E mails or mobile phone messages. ◦ Publications. ◦ Lectures or workshops. | H291: N/A | I291: N/A | J291: MCM.M.9 | K291: N/A | L291: No | P291: Data Management | Q291: 287
A303: Data Catalog and Metadata | B303: MCM | C303: MCM.MQ.3 | D303: Establishing | E303: 1 | F303: Evidence of the Existing Processes Used to Manage Metadata. | G303: The Entity must attach a document of the current Processes followed for Metadata Management (Evidence such as reports, screenshots, etc.…). | H303: N/A | I303: N/A | J303: MCM.M.13 | K303: N/A | L303: No | P303: Data Management | Q303: 299
A304: Data Catalog and Metadata | B304: MCM | C304: MCM.MQ.3 | D304: Defined | E304: 2 | F304: Metadata Identification Process Report. | G304: The Entity must attach a report showing the entity’s process for identifying and defining its business and technical metadata that will be included in the data catalog. | H304: N/A | I304: N/A | J304: MCM.M.14 | K304: N/A | L304: No | P304: Data Management | Q304: 300
A305: Data Catalog and Metadata | B305: MCM | C305: MCM.MQ.3 | D305: Defined | E305: 2 | F305: Metadata Prioritization Process Report. | G305: The Entity must attach a report showing the entity’s process for prioritizing the identified metadata. | H305: N/A | I305: N/A | J305: MCM.M.15 | K305: N/A | L305: No | P305: Data Management | Q305: 301
A306: Data Catalog and Metadata | B306: MCM | C306: MCM.MQ.3 | D306: Defined | E306: 2 | F306: Metadata Population Process Report. | G306: The Entity must attach a report showing the process for registering and populating the Metadata within the Data Catalog so that the process is implemented as a workflow within the automated data catalog tool. | H306: P2 | I306: MCM.4.2 | J306: MCM.C.4.2 | K306: No | L306: No | P306: Data Management | Q306: 302
A307: Data Catalog and Metadata | B307: MCM | C307: MCM.MQ.3 | D307: Defined | E307: 2 | F307: Metadata Update process Report. | G307: The Entity must attach a report showing the process for updating metadata in its data catalog so that the process is implemented as a workflow within the automated data catalog tool. | H307: P2 | I307: MCM.4.4 | J307: MCM.C.4.4 | K307: No | L307: No | P307: Data Management | Q307: 303
... A310: Data Catalog and Metadata | B310: MCM | C310: MCM.MQ.3 | D310: Defined | E310: 2 | F310: Metadata Certification process Report. | G310: The Entity must attach a report showing the process for regularly reviewing the trust certificates assigned by users to the Metadata within the Data Catalog so that the process is implemented as a workflow within the automated data catalog tool. | H310: P2 | I310: MCM.4.7 | J310: MCM.C.4.7 | K310: No | L310: No | P310: Data Management | Q310: 306
A318: Reference and Master Data Management | B318: RMD | C318: RMD.MQ.1 | D318: Establishing | E318: 1 | F318: The Currently Existing Practices Related to the RMD Management and Planning Domain. | G318: A report must be attached clarifying the current practices related to Reference Data management and/or Master Data management. | H318: N/A | I318: N/A | J318: RMD.M.1 | K318: N/A | L318: Yes | O318: SANS-CYB-DM-PL-02-SANS-Data Strategic Requirements and Data- Ver.1.0 Mar 2024, #64 | P318: Data Management Information Technology | Q318: 314
A319: Reference and Master Data Management | B319: RMD | C319: RMD.MQ.1 | D319: Defined | E319: 2 | F319: The Developed and Approved RMD Management Plan. | G319: A recent RMD Management Plan, approved by the entity’s authority holder must be attached including the following, at a minimum: • A roadmap that includes the activities and milestones for the Entity’s RMD Management. The activities shall incorporate what is needed to achieve this Domain’s specifications, as a minimum. • The assignment of the required resources & budget allocation to manage the implementation of the roadmap activities. | H319: P1 | I319: RMD.1.1 | J319: RMD.C.1.1 | K319: Yes | L319: Yes | O319: SANS-CYB-DM-PL-01-SANS-Data Strategy Roadmap & Investment Plan- Ver.1.0 Mar 2024, Pg. #53 | P319: Data Governance & Protection Information Technology Data Management | Q319: 315
...

Sheet Master
A4: Domain Name | B4: Domain ID | C4: NDI Q# | D4: Maturity Level | E4: Level No. | F4: Evidence | G4: Acceptance Criteria | H4: Priority | I4: NDMO Specifications | J4: NDI ID | K4: Meets NDMO criteria? | L4: Meets NDI Criteria? | M4: Compliance Validation Flag | N4: Comments | O4: Evidence Document Name | P4: Current Stakeholders
A5: Data Governance | B5: DG | C5: DG.MQ.1 | D5: Establishing | E5: 1 | F5: Existing data-related practices. | G5: Attach a report showing current data practices. | H5: N/A | I5: N/A | J5: DG.M.1 | K5: N/A | L5: Yes | O5: SANS-CYB-DM-PL-02-SANS-Data Strategic Requirements and Data- Ver.1.0 Mar 2024 | P5: Data Governance & Protection
A6: Data Governance | B6: DG | C6: DG.MQ.1 | D6: Defined | E6: 2 | F6: The approved DM & PDP Strategy. | G6: Attach the Data Management and Personal Data Protection (DM & PDP) Strategy which must be approved & includes the following, as a minimum: • Current challenges in DM. • The Strategic requirements including: Internal requirements emanating from the Entity's business strategy and external requirements emanating from the National Strategy for DM & PDP. • The DM & PDP Vision, Mission, and Strategic Objectives. • Strategic and operational performance indicators with targets extending from 3 to 5 years over the strategy’s implementation duration. • The financial budget required to implement the strategy divided according to identified initiatives. | H6: P1 | I6: DG.1.1 | J6: DG.C.1.1 | K6: Yes | L6: Yes | N6: An approved data management strategy & roadmap in place, The initiatives must align with NDMO controls for effective strategy execution and compliance monitoring. | O6: SANS-CYB-DM-PL-02-SANS-Data Strategic Requirements and Data- Ver.1.0 Mar 2024 | P6: Data Governance & Protection
A7: Data Governance | B7: DG | C7: DG.MQ.1 | D7: Defined | E7: 2 | F7: The DM guiding principles. | G7: Attach a copy of the DM & PDP program guidelines, which may be a part of the Entity's DM & PDP Strategy doc or a separate doc. The guidelines must refer to the principles underlying the culture of DM & Data processing, to enable and spread a unified DM & PDP concept within the Entity itself. | H7: P1 | I7: DG.1.2 | J7: DG.C.1.2 | K7: Yes | L7: Yes | O7: SANS-CYB-DM-PL-03-Data Strategy Mandate - Ver.1.0 Mar 2024, Page # 31 | P7: Data Governance & Protection
A8: Data Governance | B8: DG | C8: DG.MQ.1 | D8: Defined | E8: 2 | F8: Data Strategy Approval Decision letter. | G8: Attach a copy of the entity-specific data strategy approval decision by the entity’s Data Management Committee or the entity’s authority holder | H8: P1 | I8: DG.1.4 | J8: DG.C.1.4.1 | K8: Yes | L8: Yes | M8: 1 | O8: SANS-CYB-DM-PL-03-Data Strategy Mandate - Ver.1.0 Mar 2024, Page # 2 Strategy and Requirements Socialization | P8: Data Governance & Protection
A9: Data Governance | B9: DG | C9: DG.MQ.1 | D9: Activated | E9: 3 | F9: - All level 2 acceptance evidence requirements including: - The developed DM & PDP implementation plan. | G9: Attach the implementation plan which must include, as a minimum: • Identified initiatives that covers all the DM domains. • A prioritized list of DM initiatives with descriptions. • A three-year Implementation roadmap to close the gaps identified between the current state and target state. | H9: P1 | I9: DG.1.3 | J9: DG.C.1.3 | K9: Yes | L9: Yes | N9: Roadmap needs to be updated to reflect current status | O9: SANS-CYB-DM-PL-01-SANS-Data Strategy Roadmap & Investment Plan- Ver.1.0 Mar 2024 | P9: Data Governance & Protection
A10: Data Governance | B10: DG | C10: DG.MQ.1 | D10: Activated | E10: 3 | F10: Implementation status report. | G10: Attach a report of the implementation status of DM and PDP plan, including, at a minimum:  Initiatives and projects status: Identifying the status of each initiative or project (started, in progress, completed, or delayed), along with clarification of any delays or challenges.  Progress percentages: Providing the progress percentages of activities and milestones in the plan and roadmap, with clear details on the actual activities that have been completed.  Supporting evidence: Attaching proof of achieved progress/completion, such as reports, photos, documents, or meeting minutes that support the implementation status. | H10: N/A | I10: N/A | J10: DG.M.2 | K10: N/A | L10: No | P10: Data Governance & Protection
A11: Data Governance | B11: DG | C11: DG.MQ.1 | D11: Managed | E11: 4 | F11: All level 3 acceptance evidence requirements including: - The monitoring report of the DM & PDP strategy & plan implementation based on the defined KPIs in the strategy & implementation plan. | G11: The report must be prepared based on the data of the Key Performance Indicators (KPIs) (Indicator Cards) which were Predefined in the DM & PDP strategic plan, and each indicator’s data or card should include the following, as a minimum: • Indicator’s Name / Code. • Indicator’s Owner. • Indicator’s Coordinator. • Indicator’s Description. • The strategic/operational objective to be measured (with identifying the Specification or the Process to which the indicator belongs). • Indicator’s Equation. • Measurement Unit (Percentage, Number / Quantity, etc.). • Baseline (Measurement value in the first measurement year). • Target value. • Measurement Periodicity (Monthly / Quarterly / Biannually / Annually). • Data sources used to calculate the indicator. • Data collection mechanism. • Indicator’s polarity (+/-) (Positive Polarity: Higher indicator value is the target, Negative Polarity: Lower indicator value is the target). • The current value of the indicator compared to the target value. • The status of the indicator (achieved/delayed/not achieved/etc). The report should also include: • Recommendations for performance improvement based on the actual values of the indicators. • Supporting documents for the data used to calculate the indicator values. | H11: N/A | I11: N/A | J11: DG.M.3 | K11: N/A | L11: No | P11: Data Governance & Protection
A12: Data Governance | B12: DG | C12: DG.MQ.1 | D12: Pioneer | E12: 5 | F12: All level 4 acceptance evidence requirements including: - A report demonstrating the entity's monitoring of the latest DM practices and updating of the implementation plan based on these practices and changes in business requirements. | G12: Attach a report showing that the entity identified, implemented and has been monitoring the continuous improvement mechanisms for DM & PDP plan. The report shall include the following:  The updated DM & PDP strategy.  The updated DG practices that include the Data Management Organization, the roles, the processes, & the technologies.  The continuous improvement mechanisms for all DM Domains. | H12: P2 | I12: DG.6.1 | J12: DG.C.6.1 | K12: No | L12: No | P12: Data Governance & Protection
A13: Data Governance | B13: DG | C13: DG.MQ.1 | D13: Pioneer | E13: 5 | F13: A report demonstrating the entity's monitoring of the latest DM practices and updating of the strategy based on these practices and changes in business requirements. | G13: Attach a report showing that the entity identified, implemented and has been monitoring the continuous improvement mechanisms for DM & PDP strategy. The report shall include the following:  The documented periodic DM & PDP reviews & results.  Documented changes to the initial approved plan where applicable. | H13: P2 | I13: DG.7.2 | J13: DG.C.7.2 | K13: Under Development | L13: Partially | N13: The KPIs have been defined as part of the strategy, however the KPIs are not tracked | P13: Data Governance & Protection
A14: Data Governance | B14: DG | C14: DG.MQ.2 | D14: Establishing | E14: 1 | F14: The Data Management & Personal Data Protection (DM & PDP) Policies, Controls and Guidelines Gap Analysis document. | G14: The gap analysis document shall include the following as a minimum: • An analysis of DM & PDP Standards and Guidelines established by the National Data Management Office (NDMO). • Identifying & analyzing all Data-related policies & controls published by the Oversight Entities & the regulator(s) of the sector to which the Entity belongs. • An analysis of the Entity's internal requirements for DM & PDP Controls. • Recommendations and suggestions to close the gaps identified as well a specific list of policies that the Entity will develop in line with the Policies published by NDMO-SDAIA. • A plan to develop DM & PDP policies and controls, clearly presenting the implementation timeline. | H14: P1 | I14: DG.2.1 | J14: DG.C.2.1 | K14: Yes | L14: Yes | N14: All documentation mentioned. Timeline to update dm & pdp policies part of the overall roadmap (Roadmap needs to be updated) | O14: SANS-CYB-DM-PL-02-SANS-Data Strategic Requirements and Data- Ver.1.0 Mar 2024 (previously) SANS Current State Assessment Report (Latest) | P14: Data Governance & Protection
A15: Data Governance | B15: DG | C15: DG.MQ.2 | D15: Defined | E15: 2 | F15: All level 1 acceptance evidence requirements including: - The policies, standards, and guidelines developed by the entity for all DM domains. | G15: The entity should develop policies covering all DM domains, as well as standards and guidelines as needed. The policies should be approved by the Data Management and Governance Committee and every policy’s document shall include, the following, at a minimum:  Policy Name.  Release date.  Version number.  Document control (Preparation, review, approval).  Version history.  Terminology.  Goal.  Scope of work.  Guiding Principles  Policy Statement.  Job roles & responsibilities.  Related Policies.  References.  Policy Owner. - The entity should attach the policies approval evidence. | H15: P1 | I15: DG.2.2 | J15: DG.C.2.2 | K15: Under Development | L15: Partially | N15: Limited policies exists for 4 domains and not implemented | P15: Data Governance & Protection
A16: Data Governance | B16: DG | C16: DG.MQ.2 | D16: Activated | E16: 3 | F16: All level 2 acceptance evidence requirements including: - Implementation status report. | G16: Attach the policies implementation status report, showing the percentages of progress in developing the processes and procedures related to policy implementation. | H16: N/A | I16: N/A | J16: DG.M.4 | K16: N/A | L16: No | P16: Data Governance & Protection
A17: Data Governance | B17: DG | C17: DG.MQ.2 | D17: Activated | E17: 3 | F17: A document proving the Entity's approval & adoption of the developed policies, standards & guidelines. | G17: Attach a report showing the dissemination and communication of all developed policies to the relevant stakeholders of each policy (e.g., email notifications sent to relevant stakeholders to introduce the approved policies or through the entity’s official portal, etc.). | H17: N/A | I17: N/A | J17: DG.M.5 | K17: N/A | L17: No | P17: Data Governance & Protection
A18: Data Governance | B18: DG | C18: DG.MQ.2 | D18: Activated | E18: 3 | F18: Approved Compliance Management Framework. | G18: Attach the Compliance Framework, detailing the following: • The scope of the compliance audit’s periodic procedure. • The processes needed to plan and perform the compliance audit procedure. • The processes & tools needed for reporting a compliance audit results. • The processes & plans for remediating & escalating non-compliance cases. | H18: P2 | I18: DG.5.1 | J18: DG.C.5.1 | K18: Under Development | L18: Partially | N18: A draft version of compliance framework is avaiable | P18: Data Governance & Protection
A19: Data Governance | B19: DG | C19: DG.MQ.2 | D19: Managed | E19: 4 | F19: All level 3 acceptance evidence requirements including: - Monitoring reports on the developed policies and standards, based on the pre-defined KPIs related to these policies and standards, as outlined in the DM strategy and implementation plan. | G19: The entity should attach an updated report, approved by the entity’s authority holder, to monitor the performance status of the developed policies and standards based on the identified and pre-defined Key Performance Indicators (KPIs) and scorecards. Each indicator’s card should include the following at a minimum: • Indicator’s Name / Code. • Indicator’s Owner. • Indicator’s Coordinator. • Indicator’s Description. • The strategic/operational objective to be measured (with identifying the Specification or the Process to which the indicator belongs). • Indicator’s Equation. • Measurement Unit (Percentage, Number / Quantity, etc.). • Baseline (Measurement value in the first measurement year). • Target value. • Measurement Periodicity (Monthly / Quarterly / Biannually / Annually). • Data sources used to calculate the indicator. • Data collection mechanism. • Indicator’s polarity (+/-) (Positive Polarity: Higher indicator value is the target, Negative Polarity: Lower indicator value is the target). • The current value of the indicator compared to the target value. • The status of the indicator (achieved/delayed/not achieved/etc). The report should also include: • Recommendations for performance improvement based on the actual values of the indicators. • Supporting documents for the data used to calculate the indicator values. | H19: P2 | I19: DG.7.1 (3 & 6) | J19: DG.C.7.1.1 | K19: Under Development | L19: Partially | M19: 1 | N19: The KPIs have been defined as part of the strategy, however the KPIs are not tracked | P19: Data Governance & Protection
A20: Data Governance | B20: DG | C20: DG.MQ.2 | D20: Managed | E20: 4 | F20: The Entity's Compliance Audit Results Report. | G20: Attach a report documenting the results & outputs of each procedure implemented to monitor compliance. The compliance report shall include the following, at a minimum: • Compliance or Non-Compliance with each specification. • An explanation for compliance results with sufficient evidence for each specification. • Recommendations to remediate each instance of non-compliance. • Accountable stakeholder for each recommendation, and the target date to complete the recommendation. | H20: P2 | I20: DG.5.2 | J20: DG.C.5.2 | K20: Yes | L20: Yes | O20: SANS_NDMO Compliance Assessment Sheet | P20: Data Governance & Protection
A21: Data Governance | B21: DG | C21: DG.MQ.2 | D21: Managed | E21: 4 | F21: Compliance Monitoring Report. | G21: Attach a report(s) to confirm that the Entity has established and monitored compliance points by implementing a periodic compliance audit procedure. For the report to be accepted, it must be: • Compliant with the national framework for compliance in data management and governance. • Include compliance audit scores generated by the periodic compliance audits. | H21: P2 | I21: DG.5.3 | J21: DG.C.5.3 | K21: Under Development | L21: Yes | N21: NDMO assessment tool is being used for self-assessment | O21: SANS_NDMO Compliance Assessment Sheet | P21: Data Governance & Protection
A22: Data Governance | B22: DG | C22: DG.MQ.2 | D22: Pioneer | E22: 5 | F22: All level 4 acceptance evidence requirements including: - A report demonstrating the entity's innovative mechanisms for enabling compliance monitoring of DM & PDP Policies and Standards. | G22: The entity should attach the continuous improvement report for DM, DG, and PDP policies, based on the results of KPI measurements and relevant updates and developments. The report should include the following, at a minimum:  Conducted Reviews.  Results of each review.  Implemented improvements (with supporting documents).  Innovative mechanisms developed by the entity for enabling compliance monitoring of DM & PDP policies and standards. | H22: N/A | I22: N/A | J22: DG.M.6 | K22: N/A | L22: No | P22: Data Governance & Protection
A23: Data Governance | B23: DG | C23: DG.MQ.3 | D23: Establishing | E23: 1 | F23: The Entity's Data Management Office establishment decision. | G23: Attach the decision to establish a Data Management Office to supervise the implementation of the national strategy for DM, DG & PDP. To accept the attachment, the following requirements must be met:  The decision must be issued by the entity’s authority holder.  The Office’s responsibilities are documented in line with the “Organizational Manual”. | H23: P1 | I23: DG.4.1 | J23: DG.C.4.1 | K23: Yes | L23: Yes | N23: Evidence not found | O23: FW Organizational Announcement - Executives, FW Organizational Changes | P23: Data Governance & Protection
A24: Data Governance | B24: DG | C24: DG.MQ.3 | D24: Establishing | E24: 1 | F24: The appointment/hiring decisions for the following roles: A. Chief Data Officer (CDO) hiring/ appointment decision letter. | G24: To accept the attachment, the following requirements must be met:  The decision must be issued by the entity’s authority holder.  The CDO’s responsibilities are clarified in an approved job description.  The responsibilities are in line with the “Organizational Manual”. | H24: P1 | I24: DG.4.3 | J24: DG.C.4.3 | K24: Under Development | L24: Partially | N24: There is no designated individual appointed for the CDO role. however the CDO responsibilities are being carried out by the Cybersecurity, Data Governance, and Data Management Directors. There needs a confirmation from upper management regarding the decision, or documented within the target operating model | O24: Data Management Governance Committee Charter PMO, FW Organizational Announcement - Executives, Cybersecurity and Data Governance Director | P24: Data Governance & Protection
A25: Data Governance | B25: DG | C25: DG.MQ.3 | D25: Establishing | E25: 1 | F25: The appointment/hiring decisions for the following roles: B. Data Management Officer / Data Governance Officer Hiring / Appointment Decision. | G25: To accept the attachment, the following requirements must be met: • The decision must be issued by the Entity’s authority holder. • The Data Management Officer / Data Governance Officer’s responsibilities are clarified in an approved job description. • The responsibilities are in line with the "Organizational Manual”. | H25: P1 | I25: DG.4.4 | J25: DG.C.4.4 | K25: Yes | L25: Yes | O25: FW Organizational Announcement - Executives, Data Management Director V2 | P25: Data Governance & Protection
A26: Data Governance | B26: DG | C26: DG.MQ.3 | D26: Defined | E26: 2 | F26: All level 1 acceptance evidence requirements including: - Data Management & Governance Committee formation decision. | G26: To accept the attachment, the following requirements must be met:  The decision must be issued by the entity’s authority holder.  The Committee’s Charter including:  Roles and Responsibilities.  Rules of work for the committee. The decision letter must include a statement indicating that the committee's tasks involve providing guidance and overseeing the DM Strategy at the organizational level. | H26: P1 | I26: DG.4.2 | J26: DG.C.4.2 | K26: Yes | L26: Yes | O26: Data Management Governance Committee Charter PMO | P26: Data Governance & Protection
A27: Data Governance | B27: DG | C27: DG.MQ.3 | D27: Defined | E27: 2 | F27: The Hiring / Appointment decisions of the following roles: A. Compliance Officer Hiring / Appointment Decision. | G27: To accept the attachment, the following requirements must be met: • The decision must be issued by the Entity’s authority holder. • The Compliance Officer’s responsibilities are clarified in an approved job description. • The responsibilities are in line with the “Organizational Manual”. | H27: P1 | I27: DG.4.6 | J27: DG.C.4.6 | K27: Yes | L27: Yes | O27: CIS - Data Governance Section Head - updated, CIS - Data Governance and Compliance Specialist - Updated, CIS - Data Governance and Protection Manager - updated | P27: Data Governance & Protection
A28: Data Governance | B28: DG | C28: DG.MQ.3 | D28: Defined | E28: 2 | F28: The Hiring / Appointment decisions of the following roles: B. Business Data Executive Hiring / Appointment Decision. | G28: To accept the attachment, the following requirements must be met: • The decision must be issued by the Entity’s authority holder. • The Business Data Executive’s responsibilities are clarified in an approved job description. • The responsibilities are in line with the “Organizational Manual”. | H28: P1 | I28: DG.4.8 | J28: DG.C.4.8 | K28: Yes | L28: Yes | N28: Job Description exists within the target operating model, and the list of data owners have been identified. | O28: Business Data Owner & Stewards SANS_Target_State_Data_Operating_Model_v 4.0.pdf Steering Committee Presentation - 01272025 | P28: Data Governance & Protection
A29: Data Governance | B29: DG | C29: DG.MQ.3 | D29: Defined | E29: 2 | F29: The Hiring / Appointment decisions of the following roles: C. Legal Advisor Hiring / Appointment Decision. | G29: To accept the attachment, the following requirements must be met: • The decision must be issued by the Entity’s authority holder. • The Legal Advisor’s responsibilities are clarified in an approved job description. • The responsibilities are in line with the “Organizational Manual”. | H29: P1 | I29: DG.4.11 | J29: DG.C.4.11 | K29: Yes | L29: Yes | N29: Though Role exists, it needs to be clearly defined within the operating model | O29: CEO - Legal Consultations & Contracts Section Head, CEO - Legal Manager, CEO - Litigations Section Head | P29: Data Governance & Protection
A30: Data Governance | B30: DG | C30: DG.MQ.3 | D30: Activated | E30: 3 | F30: All level 2 acceptance evidence requirements including: - The Hiring / Appointment decisions of the following roles: A. Business Data Steward(s) Hiring / Appointment Decision. | G30: To accept the attachment, the following requirements must be met: • The decision must be issued by the Entity’s authority holder. • The Business Data Steward’s responsibilities are clarified in an approved job description. • The responsibilities are in line with the “Organizational Manual”. | H30: P1 | I30: DG.4.9 | J30: DG.C.4.9 | K30: Under Development | L30: Partially | N30: Job Description exists within the target operating model, and the list of business stewards have been identified,. However, the data steward list will need to be updated, and approved by upper management (formal endorsement from the committee) | O30: Business Data Owner & Stewards SANS_Target_State_Data_Operating_Model_v 4.0.pdf | P30: Data Governance & Protection
A31: Data Governance | B31: DG | C31: DG.MQ.3 | D31: Activated | E31: 3 | F31: The Hiring / Appointment decisions of the following roles: B. List of the IT Data Stewards. | G31: To accept the attachment, the following requirements must be met: • The decision must be issued by the Entity’s authority holder. • The IT Data Steward’s responsibilities are clarified in an approved job description. • The responsibilities are in line with the Organizational Manual. | H31: P1 | I31: DG.4.10 | J31: DG.C.4.10 | K31: Under Development | L31: Partially | N31: Currently technical stewards are not appointed by systems. | O31: Business Data Owner & Stewards SANS_Target_State_Data_Operating_Model_v 4.0.pdf | P31: Data Governance & Protection
A32: Data Governance | B32: DG | C32: DG.MQ.3 | D32: Activated | E32: 3 | F32: The Hiring / Appointment decisions of the following roles: C. Personal Data Protection (PDP) Officer Hiring / Appointment Decision. | G32: To accept the attachment, the following requirements must be met: • The decision must be issued by the Entity’s authority holder. • The PDP Officer’s responsibilities are clarified in an approved job description. • The responsibilities are in line with the Organizational Manual. | H32: P1 | I32: DG.4.7 | J32: DG.C.4.7 | K32: Yes | L32: Yes | N32: Job description Data Protection and Privacy section Head has been developed and approved, with additional roles as well | O32: CIS - Data Governance and Protection Manager - updated, CIS - Data Protection and Privacy Section head, CIS - Data Protection Specialist | P32: Data Governance & Protection
A33: Data Governance | B33: DG | C33: DG.MQ.3 | D33: Activated | E33: 3 | F33: The Hiring / Appointment decisions of the following roles: D. Open Data and Information Access Officer Hiring / Appointment Decision. | G33: To accept the attachment, the following requirements must be met:  The decision must be issued by the entity’s authority holder.  The ODIAO’s responsibilities are clarified in an approved job description.  The responsibilities are in line with the Organizational Manual. | H33: P1 | I33: DG.4.5 | J33: DG.C.4.5 | K33: Under Development | L33: Partially | N33: There is no appointed Open Data and Information Access Officer; responsibilities are managed by the Data Governance and Compliance Specialist per the approved job description. There needs a confirmation from upper management regarding the decision, or documented within the target operating model | O33: CIS - Data Governance and Compliance Specialist - Updated, CIS - Data Governance Section Head - updated | P33: Data Governance & Protection
A34: Data Governance | B34: DG | C34: DG.MQ.3 | D34: Activated | E34: 3 | F34: The documented & approved Data Management Organization structure. | G34: Attach the documented & approved Data Management Organization structure, including the following, as a minimum: • Roles & responsibilities. • Approved job descriptions for each role. • Authorization: Reviews, approvals and decision making. | H34: N/A | I34: N/A | J34: DG.M.7 | K34: N/A | L34: No | P34: Data Governance & Protection
A35: Data Governance | B35: DG | C35: DG.MQ.3 | D35: Activated | E35: 3 | F35: The documented Data Stewardship / Ownership structure. | G35: Attach the documented & approved Data Stewardship / Data Ownership structure, including the following, as a minimum: • Identified Data Domains. • Business Data Executives for each Data Domain. • Business Data Steward for each Data Domain. • IT Data Steward for each Data Domain. • Roles & responsibilities. | H35: N/A | I35: N/A | J35: DG.M.8 | K35: N/A | L35: No | P35: Data Governance & Protection
A36: Data Governance | B36: DG | C36: DG.MQ.3 | D36: Managed | E36: 4 | F36: All level 3 acceptance evidence requirements including - The monitoring reports for the entity's Data Management Organization roles based on the pre_x0002_defined KPIs in the strategy and implementation plan. | G36: The entity should attach an updated report approved by the entity’s authority holder to measure the entity’s performance in monitoring job roles based on the identified and pre_x0002_defined Key Performance Indicators (KPIs) and scorecards. Each indicator’s card should include the following, at a minimum: • Indicator’s Name / Code. • Indicator’s Owner. • Indicator’s Coordinator. • Indicator’s Description. • The strategic/operational objective to be measured (with identifying the Specification or the Process to which the indicator belongs). • Indicator’s Equation. • Measurement Unit (Percentage, Number / Quantity, etc.). • Baseline (Measurement value in the first measurement year). • Target value. • Measurement Periodicity (Monthly / Quarterly / Biannually / Annually). • Data sources used to calculate the indicator. • Data collection mechanism. • Indicator’s polarity (+/-) (Positive Polarity: Higher indicator value is the target, Negative Polarity: Lower indicator value is the target). • The current value of the indicator compared to the target value. • The status of the indicator (achieved/delayed/not achieved/etc). The report should also include: • Recommendations for performance improvement based on the actual values of the indicators. • Supporting documents for the data used to calculate the indicator values. | H36: P2 | I36: DG.7.1 (KPI 1) | J36: DG.C.7.1 .2 | K36: Under Development | L36: Partially | M36: 1 | N36: The KPIs have been defined as part of the strategy, however the KPIs are not tracked | P36: Data Governance & Protection
A37: Data Governance | B37: DG | C37: DG.MQ.3 | D37: Pioneer | E37: 5 | F37: All level 4 acceptance evidence requirements including: - Continuous improvement report for the roles and responsibilities of Data Management Organization within the entity. | G37: The entity must attach the continuous improvement report for the roles and responsibilities of DM Organization within the entity. The report should include the following, at a minimum:  Conducted Reviews.  Results of each review.  Implemented improvements (with supporting documents). | H37: N/A | I37: N/A | J37: DG.M.9 | K37: N/A | L37: No | P37: Data Governance & Protection
A38: Data Governance | B38: DG | C38: DG.MQ.4 | D38: Establishing | E38: 1 | F38: Evidences of communication on DM-related practices. | G38: Attach evidences showing that the entity has communications regarding Data Management practices, such as: • E-mails. • Correspondences. | H38: N/A | I38: N/A | J38: DG.M.10 | K38: N/A | L38: Yes | O38: RE_ Data Management & NDMO Requirements - Content Management, NDMO Requirements Socialization – Crisis Management & Business Continuity Team, Fw_ NDMO Requirements Details | P38: Data Governance & Protection
A39: Data Governance | B39: DG | C39: DG.MQ.4 | D39: Establishing | E39: 1 | F39: Evidences of training and awareness sessions conducted. | G39: Attach a report on the training courses & awareness programs implemented by the Entity, including the following, as a minimum: • Names of the implemented training courses related to DM, DG & PDP. • Awareness programs implemented in the different Domains under DM, DG & PDP. • A certificate of attendance sample for training the Entity’s employees in Domains related to DM, DG & PDP. | H39: N/A | I39: N/A | J39: DG.M.11 | K39: N/A | L39: Partially | N39: Training Content Created, but no tracking or list has been developed that mentions the trainings | O39: SANS Data Management Training v4 (1), SANS_Data Classification Awareness - Final Version (005) | P39: Data Governance & Protection
A40: Data Governance | B40: DG | C40: DG.MQ.4 | D40: Defined | E40: 2 | F40: All level 1 acceptance evidence requirements including: - The Change Management Plan. | G40: The Change Management Plan covering all DM Domains including: • The DM & PDP Training Plan for all DM Domains. • The DM Communication plan. • The Stakeholders engagement plan. • The Change Control plan for Data system changes. | H40: N/A | I40: N/A | J40: DG.M.12 | K40: N/A | L40: No | P40: Data Governance & Protection
A41: Data Governance | B41: DG | C41: DG.MQ.4 | D41: Activated | E41: 3 | F41: All level 2 acceptance evidence requirements including: - The Change Management Implementation Status Report showing the DM & PDP Training & Awareness Activities. | G41: Attach a report on the implementation status of the change management plan, and the report must include, as a minimum: • The DM & PDP Training implementation status for all DM Domains showing: • Evidences of training conducted for the Entity’s employees, covering all DM Domains. • A list of activities carried out by the Entity to raise awareness regarding the national regulations, laws, policies & controls, standards and their applicability (such as: e-mails, publications, lectures, workshops, etc.). • A list of activities carried out by the Entity to raise awareness regarding the national DM, DG & PDP strategy and programs and their applicability on the Entity (such as: e-mails, publications, lectures, workshops, etc.). • A list of activities carried out by the Entity to raise awareness regarding the data management domains as per the National Data Management and Personal Data Protection Framework, addressed to the related Data Management and Personal Data Protection roles. | H41: P1 | I41: DG.3.1 | J41: DG.C.3.1 | K41: Under Development | L41: No | N41: Training conducted to full time roles, but not part time roles (Data Owners, Stewards) | P41: Data Governance & Protection
A42: Data Governance | B42: DG | C42: DG.MQ.4 | D42: Activated | E42: 3 | F42: The Change Management Implementation Status Report showing the DM Communication activities. | G42: Attach a report on the implementation status of the change management plan, and the report must include evidences confirming the Entity's continuous communication regarding the following: • The DM, DG & PDP Program, activities and main decisions. • The storage of DM & DG documents & artifacts. • The measurement of DM & DG performance indicators. • The updates on DM & DG policies & processes. • The updates on compliance reports, implementation plans, and the regulatory (legislative) environment related to DM & DG. | H42: P2 | I42: DG.6.2 | J42: DG.C.6.2 | K42: No | L42: No | P42: Data Governance & Protection
A43: Data Governance | B43: DG | C43: DG.MQ.4 | D43: Activated | E43: 3 | F43: The Stakeholders Engagement and Socialization plan implementation status report. | G43: Attach a report showing that the Entity is engaging the identified stakeholders to develop and improve on the capabilities of the DM & PDP program. | H43: P1 | I43: DG.1.4 | J43: DG.C.1.4.2 | K43: Yes | L43: Yes | M43: 1 | O43: RE_ Data Management & NDMO Requirements - Content Management, NDMO Requirements Socialization – Crisis Management & Business Continuity Team, Fw_ NDMO Requirements Details | P43: Data Governance & Protection
A44: Data Governance | B44: DG | C44: DG.MQ.4 | D44: Activated | E44: 3 | F44: The Data Governance Approvals Register. | G44: The register should include, as a minimum: • CDO’s DG Decisions with their rationalized constituents. • DM & DG Committee Decisions. | H44: P2 | I44: DG.8.1 | J44: DG.C.8.1 | K44: Under Development | L44: Partially | N44: Data Governance Approvals Register template exist. However the decisions are not documented | O44: SANS-CYB-MD-PMM01-FO-03-Data Governance Approvals Register-Rev.A-Oct 2024 | P44: Data Governance & Protection
A45: Data Governance | B45: DG | C45: DG.MQ.4 | D45: Activated | E45: 3 | F45: The Data Management Issue Tracking Register. | G45: The register should include, as a minimum: • A sample of DM & DG issues reported by business & technical users. • Evidence of resolution of the reported issues. | H45: P3 | I45: DG.8.2 | J45: DG.C.8.2 | K45: Under Development | L45: Partially | N45: Issue Tracking Registe template exist. However the data issues are not documented | O45: SANS-CYB-DM-POL07-FO-01-SANS Data Governance and Management Issue Tracking Register-Rev.A-Nov 2024 | P45: Data Governance & Protection
A46: Data Governance | B46: DG | C46: DG.MQ.4 | D46: Activated | E46: 3 | F46: Evidences that the Entity has DM & DG document & artifact Version Control practices. | G46: Attach a sample of a register / record or a document created by the Entity, and it must include the following as a minimum: • The Domain name of the registry. • The Registry’s Issuance Date. • The Registry’s Updating Dates. • The Registry Versions Control. • The Updates made to the Registry or document. | H46: P2 | I46: DG.8.3 | J46: DG.C.8.3 | K46: Yes | L46: Yes | N46: Needs confirmation of applying version control practiaces within the SANS Portal | O46: SANS-SQE-PMM-01 Quality Management Manual ver.3.4 Dec 2024, SANS-SQE-PMM01-FO-01 Document Change, | P46: Data Governance & Protection
A47: Data Governance | B47: DG | C47: DG.MQ.4 | D47: Managed | E47: 4 | F47: All level 3 acceptance evidence requirements including: - The monitoring report of the change management practices with pre_x0002_defined KPIs in the Change Management Plan | G47: A report on monitoring the Change Management activities & practices should be attached based on Predefined KPIs, which include, as a minimum, the following indicators: 1- The Indicator of the periodic meetings of the internal DM & DG & PDP committee. 2- The Indicator of the completed training & awareness sessions. 3- The Indicator of the attendance rates in the completed training & awareness sessions. 4- The duration Indicator of the DM & PDP issue resolutions. 5- The quantity Indicator of the number of resolved & closed change requests. 6- The Indicator of the number of Data Sharing requests received. Each indicator’s data or card must include the following, as a minimum: • Indicator’s Name / Code. • Indicator’s Owner. • Indicator’s Coordinator. • Indicator’s Description. • The strategic/operational objective to be measured (with identifying the Specification or the Process to which the indicator belongs). • Indicator’s Equation. • Measurement Unit (Percentage, Number / Quantity, etc.). • Baseline (Measurement value in the first measurement year). • Target value. • Measurement Periodicity (Monthly / Quarterly / Biannually / Annually). • Data sources used to calculate the indicator. • Data collection mechanism. • Indicator’s polarity (+/-) (Positive Polarity: Higher indicator value is the target, Negative Polarity: Lower indicator value is the target). • The current value of the indicator compared to the target value. • The status of the indicator (achieved/delayed/not achieved/etc). The report should also include: • Recommendations for performance improvement based on the actual values of the indicators. • Supporting documents for the data used to calculate the indicator values. | H47: P2 | I47: DG.7.1 (KPIs 2, 4, 5, 7 & 8) | J47: DG.C.7.1.3 | K47: Under Development | L47: No | M47: 1 | N47: The KPIs have been defined as part of the strategy, however the KPIs are not tracked | P47: Data Governance & Protection
A48: Data Governance | B48: DG | C48: DG.MQ.4 | D48: Pioneer | E48: 5 | F48: All level 4 acceptance evidence requirements including: - Continuous improvement report of the change management, highlighting the innovative mechanisms contributing to change management in areas related to data management. | G48: The entity should attach the continuous improvement report for change management practices, based on the results of KPI measurements and the innovative mechanisms and methods developed by the entity to enhance the effectiveness of change management. The report should include the following, at a minimum:  Conducted Reviews.  Results of each review.  Implemented improvements (with supporting documents).  Innovative mechanisms and methods related to change management. | H48: N/A | I48: N/A | J48: DG.M.13 | K48: N/A | L48: No | P48: Data Governance & Protection
A49: Data Classification | B49: DC | C49: DC.MQ.1 | D49: Establishing | E49: 1 | F49: The Existing DC Practices. | G49: The Entity must attach a report clarifying the current Data Classification Practices. | H49: N/A | I49: N/A | J49: DC.M.1 | K49: N/A | L49: Yes | O49: SANS-CYB-DM-PL-02-SANS-Data Strategic Requirements and Data- Ver.1.0 Mar 2024, Page # 86 | P49: Data Governance & Protection
A50: Data Classification | B50: DC | C50: DC.MQ.1 | D50: Defined | E50: 2 | F50: The defined & Approved Data Classification Plan. | G50: The Data Classification Plan must include the following, as a minimum: • The roadmap with the activities & milestones for the classification of Entity's Data. The activities shall incorporate what is needed to achieve this Domain’s specifications, as a minimum. • The assignment of the required resources & budget to manage the classification of the Entity's data. | H50: P1 | I50: DC.1.1 | J50: DC.C.1.1 | K50: Yes | L50: Yes | O50: SANS-CYB-DM-PL-01-SANS-Data Strategy Roadmap & Investment Plan- Ver.1.0 Mar 2024, Page # 45 | P50: Data Governance & Protection
A51: Data Classification | B51: DC | C51: DC.MQ.1 | D51: Activated | E51: 3 | F51: The Data Classification implementation plan status report. | G51: The Entity must attach a report clarifying the status of Data Classification implementation plan. The report must include, at a minimum, the following: • Initiative and Project Status: Indicate the status of each initiative or project (not started, in progress, completed, or delayed), along with details of any delays or challenges. • Progress Percentages: Provide progress percentages for the activities and milestone objectives outlined in the plan and roadmap, with clear details on the actual activities that have been executed. • Supporting Evidence: Attach proof of progress/achievements, such as reports, images, documents, or meeting minutes that substantiate the implementation status. | H51: N/A | I51: N/A | J51: DC.M.2 | K51: N/A | L51: No
A52: Data Classification | B52: DC | C52: DC.MQ.1 | D52: Managed | E52: 4 | F52: The Implementation Monitoring Report of the DC Plan & Activities with Predefined KPIs. | G52: The entity must attach an updated report, approved by the entity’s authority holder, on monitoring the effectiveness of the Data Classification plan based on pre-defined and identified KPIs and indicator cards. Each indicator’s data or card must include the following, as a minimum: • Indicator’s Name / Code. • Indicator’s Owner. • Indicator’s Coordinator. • Indicator’s Description. • The strategic/operational objective to be measured (with identifying the Specification or the Process to which the indicator belongs). • Indicator’s Equation. • Measurement Unit (Percentage, Number / Quantity, etc.). • Baseline (Measurement value in the first measurement year). • Target value. • Measurement Periodicity (Monthly / Quarterly / Biannually / Annually). • Data sources used to calculate the indicator. • Data collection mechanism. • Indicator’s polarity (+/-) (Positive Polarity: Higher indicator value is the target, Negative Polarity: Lower indicator value is the target). • The current value of the indicator compared to the target value. • The status of the indicator (achieved/delayed/not achieved/etc). The report should also include: • Recommendations for performance improvement based on the actual values of the indicators. • Supporting documents for the data used to calculate the indicator values. | H52: N/A | I52: N/A | J52: DC.M.3 | K52: N/A | L52: No
A53: Data Classification | B53: DC | C53: DC.MQ.1 | D53: Pioneer | E53: 5 | F53: Data classification plan review report. | G53: The Entity must attach a report showing that the Entity identified, implemented and monitored continuous improvement mechanisms for the Data Classification Plan, based on the results of performance indicator measurements and relevant developments and updates in the field. The report must include at least the following: • Reviews conducted. • Results of each review. • Improvements implemented (with supporting documentation). | H53: N/A | I53: N/A | J53: DC.M.4 | K53: N/A | L53: No
A54: Data Classification | B54: DC | C54: DC.MQ.2 | D54: Establishing | E54: 1 | F54: The Current List of Classified Datasets. | G54: The Entity must attach the current classified Datasets list. | H54: N/A | I54: N/A | J54: DC.M.5 | K54: N/A | L54: Yes | O54: DM Screenshort SANS Data Classification Register_V1, SANS Department data register - Data Managment_v2 Final (DC.MQ.1), DC.MQ.2 | P54: Data Governance & Protection
A55: Data Classification | B55: DC | C55: DC.MQ.2 | D55: Defined | E55: 2 | F55: Data Classification Policy. | G55: Attach a data classification policy, which should include at a minimum: • Policy name. • Release date. • Release number. • Document control (preparation, revision, approval). • Version history. • Terminology. • Objective. • Scope of work. • References. • Policy owner. • Policy statement including as a minimum: ◦ The main principles of classification ◦ Classification prioritization process and criteria ◦ Classification levels ◦ Classification controls ◦ Steps required for classification: 1. Define data. 2. Appointing the classification officer. 3. Conduct an impact assessment. 4. Conduct an impact assessment for low-impact data. 5. Classification review. 6. Apply appropriate controls. 7. Roles and responsibilities | H55: N/A | I55: N/A | J55: DC.M.6 | K55: N/A | L55: Yes | O55: SANS-CYB-DM-POL-01 SANS - Data Classification - Policy Ver 1.1-Apr 2025 | P55: Data Governance & Protection
A56: Data Classification | B56: DC | C56: DC.MQ.2 | D56: Defined | E56: 2 | F56: The Data Handling and Protection Controls. | G56: The Entity must attach a document containing the Handling & Protection Controls for each Dataset & Artifact according to its classification, to ensure secure handling, processing, sharing and disposal of data by following the policies & regulations of the National Cybersecurity Authority (NCA). The document shall include, as a minimum: • The controls for protection, handling & processing of Public Classification cases. • The controls for protection, handling & processing of Restricted Classification cases. • The controls for protection, handling & processing of Confidential / Secret Classification cases. • The controls for protection, handling & processing of Top Confidential / Top Secret Classification cases. | H56: As specified by NCA | I56: DC.2.1 | J56: DC.C.2.1 | K56: Under Development | L56: Yes | O56: SANS-CYB-GL-01 SANS - Data Classification Handling Guidelines-Ver 1.0- Apr 2025 | P56: Data Governance & Protection
A57: Data Classification | B57: DC | C57: DC.MQ.2 | D57: Activated | E57: 3 | F57: The Inventory Report of the Identified Datasets and Artifacts. | G57: The Entity must attach a document clarifying an inventory of all Datasets & Artifacts to implement the Data Classification Process, including as a minimum: • Identifying the ownership of the Datasets & Artifacts. • The list of all Datasets & Artifacts. | H57: P1 | I57: DC.3.1 | J57: DC.C.3.1 | K57: Yes | L57: Yes | O57: SANS Data Classification Register_V1 | P57: Data Governance & Protection
A58: Data Classification | B58: DC | C58: DC.MQ.2 | D58: Activated | E58: 3 | F58: The Prioritized Datasets and Artifacts. | G58: The Entity must attach a document showing the list of prioritized Datasets & Artifacts to be followed during classification. | H58: P1 | I58: DC.1.2 | J58: DC.C.1.2 | K58: Yes | L58: Yes | O58: SANS Data Classification Register_V1 | P58: Data Governance & Protection
A59: Data Classification | B59: DC | C59: DC.MQ.2 | D59: Activated | E59: 3 | F59: The Impact Assessment Report. | G59: The Entity must attach a report proving that the Entity conducts probable impact assessments (e.g., Any potential damage) when disclosing specific Data or when specific Data was accessed in an unauthorized way. The Impact Assessment process should be implemented for all identified Datasets & Artifacts, including the following steps: • The identification of the potential categories impacted, amongst national interests, organizations, individuals and environment. • The selection of the potential damage impact level for each identified category amongst 'High', 'Medium', 'Low' and 'None / Insignificant'. • The assignment of Classification Levels to Datasets & Artifacts based on the selected impact level: ◦ If the impact level was assessed as 'High', then Datasets & Artifacts shall be classified as Top Confidential / Top Secret. ◦ If the impact level was assessed as 'Medium', then Datasets & Artifacts shall be classified as Confidential / Secret. ◦ If the impact level was assessed as 'Low', then Datasets & Artifacts shall be classified as Restricted. ◦ If the impact level was assessed as 'None / Insignificant', then Datasets & Artifacts shall be classified as Public. • The assessment alignment with the Data Classification Policies & Regulations published by NDMO-SDAIA. | H59: P1 | I59: DC.3.2 | J59: DC.C.3.2 | K59: Yes | L59: Yes | O59: SANS Data Classification Register_V1 | P59: Data Governance & Protection
A60: Data Classification | B60: DC | C60: DC.MQ.2 | D60: Activated | E60: 3 | F60: The Assessment Report of Low Impact Data. | G60: A report shall be attached proving that the Entity researched / assessed the possibility of Classifying Low-impact Data as Public instead of Restricted. The assessment shall include the following: • Analyzing / evaluating if the disclosure of this Low-impact data breaches any existing KSA regulation such as the Anti Cyber Crime Regulations and the Electronic Commerce (e-Commerce) Regulations. • Identifying the potential benefits of disclosing / opening such Datasets & Artifacts and assuring / considering whether those would outweigh the negative impacts. • Modifying the Low-impact classified data to be considered Public if publishing / releasing would not breach any applicable / existing regulation, especially if the benefits outweigh the negative impacts. • Aligning the assessment with the Data Classification Policies & Regulations published by NDMO-SDAIA. | H60: P1 | I60: DC.3.3 | J60: DC.C.3.3 | K60: Yes | L60: Yes | O60: SANS Data Classification Register_V1 | P60: Data Governance & Protection
A61: Data Classification | B61: DC | C61: DC.MQ.2 | D61: Activated | E61: 3 | F61: Evidences of Utilization of the Data Catalog Tool for the Data Inventory. | G61: The Entity must attach a report or a proof that the Data Catalog Tool was used for Data Inventorying. | H61: N/A | I61: N/A | J61: DC.M.7 | K61: N/A | L61: No
A62: Data Classification | B62: DC | C62: DC.MQ.2 | D62: Activated | E62: 3 | F62: The Approved Data Access List of users with the Assigned Privileges. | G62: The Entity must attach a document showing the Data Access list with the assigned permissions / privileges, including the following, as a minimum: • Specifying the types of users who need Data Access. • Specifying the Data Access Authorizations (Read, Modify, Delete). | H62: N/A | I62: N/A | J62: DC.M.8 | K62: N/A | L62: No
A63: Data Classification | B63: DC | C63: DC.MQ.2 | D63: Activated | E63: 3 | F63: Data Register | G63: The Entity must attach a register / log documenting the list of all identified Datasets & Artifacts, in addition to the activities implemented during the Data Classification process. The register / log should include the following, as a minimum: • The list of the Entity's identified Datasets & Artifacts. • The Classification Levels assigned to the identified Datasets & Artifacts. • The Assignment Dates of the classification levels to the identified Datasets & Artifacts. • The mandatory Classification Durations of the identified Datasets & Artifacts. • The Classification Levels approved / validated during the reviews. • The Classification Levels' Review Dates. | H63: P2 | I63: DC.5.1 | J63: DC.C.5.1 | K63: Yes | L63: Yes | O63: SANS Data Classification Register_V1
A64: Data Classification | B64: DC | C64: DC.MQ.2 | D64: Managed | E64: 4 | F64: The Monitoring Report of the DC Processes with Predefined KPIs. | G64: The entity must attach an updated and authorized report by the responsible authority to monitor the effectiveness of the Data Classification Processes, based on the predefined and identified Key Performance Indicators (KPIs) and scorecards, including the following KPIs, as a minimum: • The percentage of Classified Datasets & Artifacts (out of the Entity’s total Datasets & Artifacts). • The percentage of Datasets & Artifacts classified with specific classification levels (out of the Entity’s total Classified Datasets & Artifacts). • The percentage of Low-impact data classified as Restricted. • The percentage of Classified Datasets & Artifacts that were reviewed, approved & validated. Each indicator’s data or card must include the following, as a minimum: • Indicator’s Name / Code. • Indicator’s Owner. • Indicator’s Coordinator. • Indicator’s Description. • The strategic / operational objective to be measured (with identifying the Specification or the Process to which the indicator belongs). • Indicator’s Equation. • Measurement Unit (Percentage, Number / Quantity, etc.). • Baseline (Measurement value in the first measurement year). • Target value. • Measurement Periodicity (Monthly / Quarterly / Biannually / Annually). • Data sources used to calculate the indicator. • Data collection mechanism. • Indicator’s polarity (+/-) (Positive Polarity: Higher indicator value is the target, Negative Polarity: Lower indicator value is the target). • The current value of the indicator compared to the target value. • The status of the indicator (achieved/delayed/not achieved/etc). The report should also include: • Recommendations for performance improvement based on the actual values of the indicators. • Supporting documents for the data used to calculate the indicator values. | H64: P2 | I64: DC.4.1 | J64: DC.C.4.1 | K64: No | L64: No
A65: Data Classification | B65: DC | C65: DC.MQ.2 | D65: Pioneer | E65: 5 | F65: The Data Classification Automation Tool. | G65: The entity must attach a report that includes at least the following: • A description of the solutions and tools used in the data classification automation process. • A description of the processes and stages of data classification automation. • Samples of the tools used in the data classification automation process. • Samples of the data classified using data classification automation tools. | H65: N/A | I65: N/A | J65: DC.M.9 | K65: N/A | L65: No
A66: Data Classification | B66: DC | C66: DC.MQ.3 | D66: Establishing | E66: 1 | F66: The Current Practices of DC Reviews. | G66: The Entity must attach a report clarifying the current practices of reviewing the classification of all Classified Datasets & Artifacts for the following: • To ensure that the assigned classification level for each is suitable, in line with the Data Classification Policies & Regulations. • To change the classification level if the Data status changes. | H66: N/A | I66: N/A | J66: DC.M.10 | K66: N/A | L66: Yes | O66: SANS-CYB-DM-PMM-01SANS - Data Classification - Process Ver 1.1-Apr 2025 | P66: Data Governance & Protection
A67: Data Classification | B67: DC | C67: DC.MQ.3 | D67: Defined | E67: 2 | F67: The DC Review Mechanism. | G67: The entity must attach a document specifying the Data Classification Review Mechanism, as well as the roles and responsibilities related to all stages of the classification review process, in accordance with the Data Classification Policy. The document must include, at a minimum, the following:  Procedures for verifying the accuracy of the data collected.  Procedures for verifying data classification levels.  Procedures for verifying validity.  Procedures for Identifying errors and corrections.  Procedures for documenting the Data Classification Review Process. | H67: N/A | I67: N/A | J67: DC.M.11 | K67: N/A | L67: No | N67: The provided evidence does not align with NDI requirements. | O67: SANS-CYB-DM-PMM-01SANS - Data Classification - Process Ver 1.1-Apr 2025 | P67: Data Governance & Protection
A68: Data Classification | B68: DC | C68: DC.MQ.3 | D68: Activated | E68: 3 | F68: The Data Classification Review Report. | G68: The entity must attach a report that proves periodic Data Classification reviews in accordance with the defined classification review mechanism and the Data Classification Policy issued by NDMO-SDAIA. The report must, at a minimum, include the following: • The Reviewed Classified Datasets & Artifacts. • The Decisions made resulting from the Review Process. | H68: P2 | I68: DC.3.4 | J68: DC.C.3.4 | K68: Under Development | L68: No
A69: Data Classification | B69: DC | C69: DC.MQ.3 | D69: Activated | E69: 3 | F69: An Evidence Document of the Published Classification Levels as Metadata. | G69: The Entity must attach a document proving that the Entity published on the comprehensive Data Catalog the classification levels assigned to the Datasets. The Metadata must be published according to the process defined in the Data Catalog & Metadata (MCM) Data Management (DM) Domain (i.e., Metadata & Catalog Management (MCM)). | H69: P2 | I69: DC.3.5 | J69: DC.C.3.5 | K69: No | L69: No
A70: Data Classification | B70: DC | C70: DC.MQ.3 | D70: Managed | E70: 4 | F70: The Monitoring Report of the DC Review Mechanism with Predefined KPIs. | G70: The entity must attach an updated report, approved by the entity’s authority holder, on monitoring the effectiveness of the DC Review Mechanism based on pre-defined and identified KPIs and indicator cards Each indicator’s data or card must include the following, as a minimum: • Indicator’s Name / Code. • Indicator’s Owner. • Indicator’s Coordinator. • Indicator’s Description. • The strategic / operational objective to be measured (with identifying the Specification or the Process to which the indicator belongs). • Indicator’s Equation. • Measurement Unit (Percentage, Number / Quantity, etc.). • Baseline (Measurement value in the first measurement year). • Target value. • Measurement Periodicity (Monthly / Quarterly / Biannually / Annually). • Data sources used to calculate the indicator. • Data collection mechanism. • Indicator’s polarity (+/-) (Positive Polarity: Higher indicator value is the target, Negative Polarity: Lower indicator value is the target). • The current value of the indicator compared to the target value. • The status of the indicator (achieved/delayed/not achieved/etc). The report should also include: • Recommendations for performance improvement based on the actual values of the indicators. • Supporting documents for the data used to calculate the indicator values. | H70: N/A | I70: N/A | J70: DC.M.12 | K70: N/A | L70: No
A71: Data Classification | B71: DC | C71: DC.MQ.3 | D71: Pioneer | E71: 5 | F71: Data classification review mechanisms review report. | G71: The entity must attach a continuous improvement report for data classification review, based on the results of performance indicator measurements, as well as relevant updates and developments in the field. The report must include, at a minimum, the following: • Evidence of the automation of data classification review processes and the automated reflection of the new classification on the data catalog tool. • Review and results documentation: Periodic review and results documentation for data classification review. • Continuous improvement mechanisms: Mechanisms for the continuous improvement of data classification review. | H71: N/A | I71: N/A | J71: DC.M.13 | K71: N/A | L71: No | O71: No relevant evidence present
A72: Data Sharing and Interoperability | B72: DSI | C72: DSI.MQ.1 | D72: Establishing | E72: 1 | F72: The Names of the Current Practices of Data Sharing and Integration (DSI). | G72: The Entity must attach a list of the names of the current DSI Practices and Activities, including an evidence to support the practice of each Activity, being one of the following, as a minimum: • Email copies / screenshots. • Document Copies. • System screenshots. | H72: N/A | I72: N/A | J72: DSI.M.1 | K72: N/A | L72: Yes | O72: SANS-CYB-DM-PL-02-SANS-Data Strategic Requirements and Data- Ver.1.0 Mar 2024 | P72: Data Governance & Protection
A73: Data Sharing and Interoperability | B73: DSI | C73: DSI.MQ.1 | D73: Establishing | E73: 1 | F73: The Updated and Approved Results of the Initial Data Integration Assessment. | G73: The Entity must attach the report of the Data Integration assessment results, including the following, as a minimum: • The current IT Structure: an inventory of all existing IT components (data sources, systems, applications and data stores). • High Level Data Lineage including the rules according to which data is changed, and the frequency of changes. • Data Models used by the Entity's IT components. • List of all identified challenges in the Data Lineage of data movements and integration. | H73: N/A | I73: DSI.1.1 | J73: DSI.C.1.1 | K73: Under Development | L73: Partially | N73: Does not cover all requirements | O73: Integration_assessment | P73: Information Technology Data Management
A74: Data Sharing and Interoperability | B74: DSI | C74: DSI.MQ.1 | D74: Defined | E74: 2 | F74: The Developed Data Integration Strategy Document. | G74: The entity must attach the developed Data Integration Strategy containing the following, at a minimum:  The Strategy’s approval by the entity’s authority holder and effective date.  The Strategy must be recent (Approved within the last three years).  The objectives, initiatives, projects and the metric indicators of the implementation of the Data Integration activities and milestones. The activities shall incorporate what is needed to achieve this Domain’s specifications, at a minimum.  The implementation roadmap of the Data Integration initiatives.  The assignment of the required resources & budget allocation to manage the implementation of this Domain. | H74: N/A | I74: N/A | J74: DSI.M.2 | K74: N/A | L74: No | P74: Information Technology Data Management
A75: Data Sharing and Interoperability | B75: DSI | C75: DSI.MQ.1 | D75: Defined | E75: 2 | F75: The Developed Target Data Integration Architecture. | G75: The Entity must attach the Target Data Integration Architecture including the following, as a minimum: • The Data Integration requirements. • The Data Integration Architecture diagram. • The Architecture components. | H75: P1 | I75: DSI.1.2 | J75: DSI.C.1.2 | K75: No | L75: No | P75: Information Technology Data Management
A76: Data Sharing and Interoperability | B76: DSI | C76: DSI.MQ.1 | D76: Defined | E76: 2 | F76: The Developed Data Integration Plan (Including Data Sharing Activities). | G76: The Entity must attach the developed Data Integration Plan including the following, as a minimum: • The summarized Architecture briefs. • The roadmap and covenant charters of the projects and initiatives in the plan. • The assignment of the required resources & budget allocation for the projects and initiatives in the plan. | H76: P1 | I76: DSI.1.3 | J76: DSI.C.1.3 | K76: Under Development | L76: Partially | N76: Roadmap needs to be updated to include summarized architecture briefs | O76: SANS-CYB-DM-PL-02-SANS-Data Strategic Requirements and Data- Ver.1.0 Mar 2024 | P76: Information Technology Data Management
A77: Data Sharing and Interoperability | B77: DSI | C77: DSI.MQ.1 | D77: Defined | E77: 2 | F77: The Developed Data Sharing Policies. | G77: The entity must attach the updated Policies of the Data Sharing & Interoperability (DSI) Domain, approved by the entity’s authority holder. The developed policies must align with the updated National Data Governance policies issued by the National Data Management Office (NDMO) - SDAIA. - Every Policy document must include, the following, as a minimum: • Policy title / name. • Policy owner. • Release date. • Version number. • Version history. • Objective. • Identified stakeholders. • Communications process. • Document control (Preparation, review, approval). • Policy Statement. • Roles & responsibilities. • Terminology. • Scope of work. • Activation mechanisms. • Target audience. • Approval. • References. | H77: N/A | I77: N/A | J77: DSI.M.3 | K77: N/A | L77: No | P77: Data Governance & Protection
A78: Data Sharing and Interoperability | B78: DSI | C78: DSI.MQ.1 | D78: Defined | E78: 2 | F78: The Developed Data Sharing Training Plan. | G78: The Entity must attach the developed and approved DSI Domain’s training and awareness plan including the following, as a minimum: • The training and awareness programs plan implementation dates. • The objectives of training and awareness including, as a minimum, the topics stated in the “Data Management and Personal Data Protection (DM & PDP) Standards” document i.e. ◦ Introduction on the applicability of the Data Sharing process. ◦ The leading / best Data Sharing practices. ◦ The consequences of mishandling Data. ◦ The Data Sharing Standards, Controls & Principles. • The methods and channels through which the trainings will be conducted. • Identifying the DSI Domain Awareness campaign channels, which include: ◦ E mails or mobile phone messages. ◦ Publications. ◦ Lectures or workshops. | H78: N/A | I78: N/A | J78: DSI.M.4 | K78: N/A | L78: No | N78: Data Sharing Domain covered on a very high level in the Data Management Training. But this cannot be considered as an evidence for this line item, since it requires more detailed training material and training plan. | O78: SANS Data Management Training v4 (1) | P78: Data Governance & Protection
A79: Data Sharing and Interoperability | B79: DSI | C79: DSI.MQ.1 | D79: Activated | E79: 3 | F79: A Data Integration Plan Implementation Status Report. | G79: The entity must attach an updated and approved report on the implementation status of the DSI Plan and roadmap, containing the following, at a minimum:  Initiatives and projects status: Identifying the status of each initiative or project (started, in progress, completed, or delayed), along with clarification of any delays or challenges.  Progress percentages: Providing the progress percentages of activities and milestones in the plan and roadmap, with clear details on the actual activities that have been completed.  Supporting evidence: Attaching proof of achieved progress/completion, such as reports, photos, documents, or meeting minutes that support the implementation status. | H79: N/A | I79: N/A | J79: DSI.M.5 | K79: N/A | L79: No | P79: Data Governance & Protection Data Management
A80: Data Sharing and Interoperability | B80: DSI | C80: DSI.MQ.1 | D80: Activated | E80: 3 | F80: A Progress Report on Data Sharing Training Programs. | G80: The Entity must attach an updated and approved report clarifying the DSI training & awareness implementation status containing the following, as a minimum: • The training and awareness target audience. • The list of conducted training programs and awareness campaigns (Including the topics of the programs, the dates when they were conducted, and the names of the training attendants). • Samples of the activities performed by the Entity to raise awareness about the DSI Domain, including: ◦ E mails or mobile phone messages. ◦ Publications. ◦ Lectures or workshops. | H80: P2 | I80: DSI.2.1 | J80: DSI.C.2.1 | K80: No | L80: No | P80: Data Governance & Protection
A81: Data Sharing and Interoperability | B81: DSI | C81: DSI.MQ.1 | D81: Activated | E81: 3 | F81: A Report on the Defined Roles and Responsibilities for DSI. | G81: The entity must attach an updated report, approved by the entity’s authority holder presenting the DSI Domain’s roles and responsibilities including the following, at a minimum:  The stewardship roles of the DSI processes.  The stewardship responsibilities of the DSI processes.  A list of individuals assigned to carry out the roles and responsibilities for the domain. | H81: N/A | I81: N/A | J81: DSI.M.6 | K81: N/A | L81: No | N81: Data steward role is not formalized | P81: Data Governance & Protection
A82: Data Sharing and Interoperability | B82: DSI | C82: DSI.MQ.1 | D82: Managed | E82: 4 | F82: The Monitoring Report with Pre-defined Key Performance Indicators (KPIs) for the Data Integration Plan and Data Sharing Activities. | G82: The entity must attach an updated report, approved by the entity’s authority holder on monitoring the effectiveness of the DSI domain implementation plan based on pre-defined and identified KPIs and indicator cards. - Each indicator’s data or card should include the following, as a minimum: • Indicator’s Name / Code. • Indicator’s Owner. • Indicator’s Coordinator. • Indicator’s Description. • The strategic / operational objective to be measured (with identifying the Specification or the Process to which the indicator belongs). • Indicator’s Equation. • Measurement Unit (Percentage, Number / Quantity, etc.). • Baseline (Measurement value in the first measurement year). • Target value. • Measurement Periodicity (Monthly / Quarterly / Biannually / Annually). • Data sources used to calculate the indicator. • Data collection mechanism. • Indicator’s polarity (+/-) (Positive Polarity: Higher indicator value is the target, Negative Polarity: Lower indicator value is the target). • The current value of the indicator compared to the target value. • The status of the indicator (achieved/delayed/not achieved/etc). The report should also include: • Recommendations for performance improvement based on the actual values of the indicators. • Supporting documents for the data used to calculate the indicator values. | H82: N/A | I82: N/A | J82: DSI.M.7 | K82: N/A | L82: No | P82: Data Governance & Protection Data Management
A83: Data Sharing and Interoperability | B83: DSI | C83: DSI.MQ.1 | D83: Pioneer | E83: 5 | F83: The Continuous Improvement Report on the Data Integration Plan and Data Sharing Activities. | G83: he entity must attach an updated report, approved by the entity’s authority holder presenting the continuous improvements of the DSI Domain’s plan based on the results of the KPI measurements and relevant updates and developments in the domain containing the following, at a minimum:  The conducted reviews.  The results of each review.  The implemented enhancements (with supporting documents) | H83: N/A | I83: N/A | J83: DSI.M.8 | K83: N/A | L83: No | P83: Data Governance & Protection Data Management
A84: Data Sharing and Interoperability | B84: DSI | C84: DSI.MQ.2 | D84: Establishing | E84: 1 | F84: Evidences of the Current DSI Practices / Processes by the Entity (Internally & Externally). | G84: The Entity must attach a report on the current DSI Practices and Processes, both internally within the Entity and externally with other Entities, including an evidence to support the practice of each Activity / Process, being one of the following, as a minimum: • Email copies / screenshots. • Document Copies. • System screenshots. | H84: N/A | I84: N/A | J84: DSI.M.9 | K84: N/A | L84: Yes | O84: SANS-CYB-PMM18- Data Sharing - Ver. 2.0- Apr 2025 | P84: Data Governance & Protection
A85: Data Sharing and Interoperability | B85: DSI | C85: DSI.MQ.2 | D85: Defined | E85: 2 | F85: The Process Documentation for Data Sharing (Including Data Classification Levels and Timelines). | G85: The Entity must attach the Data Sharing Process documents with the Process details including the following, as a minimum: • Data Sharing Request Reception. • Identification / assignment of roles. • Data Classification (DC) level check. • Data Sharing Principles assessment. • Data sharing decision and replying with feedback. • Business Data Executive’s approval. • Design and implementation of Data Sharing Controls. • Data Sharing Agreement signing. • Sharing Data with the Requestor. | H85: P1 | I85: DSI.5.1 | J85: DSI.C.5.1.1 | K85: Under Development | L85: Partially | M85: 1 | N85: The provided evidence does not align with NDI requirements. The following gaps identified : -No separate process for internal and external data sharing -Data Sharing Principles assessment is absent. -No Data Sharing Agreement signing. | O85: SANS-CYB-PMM18- Data Sharing - Ver. 2.0- Apr 2025 | P85: Data Governance & Protection
A86: Data Sharing and Interoperability | B86: DSI | C86: DSI.MQ.2 | D86: Defined | E86: 2 | F86: The Developed and Approved Data Sharing Request Forms (Internal and External). | G86: The Entity must attach the Forms of the internal and external Data Sharing requests using the Entity’s approved templates. | H86: N/A | I86: N/A | J86: DSI.M.10 | K86: N/A | L86: Yes | O86: SANS-CYB-PMM18-FO-01- Data Sharing Request Form- Ver.B - Apr 2025 (1) | P86: Data Governance & Protection
A87: Data Sharing and Interoperability | B87: DSI | C87: DSI.MQ.2 | D87: Defined | E87: 2 | F87: The Developed and Approved Internal Data Sharing Agreement Template. | G87: The Entity must attach the internal Data Sharing Agreements between information systems within the Entity. | H87: P2 | I87: DSI.7.1 | J87: DSI.C.7.1.1 | K87: No | L87: No | M87: 1 | P87: Data Governance & Protection
A88: Data Sharing and Interoperability | B88: DSI | C88: DSI.MQ.2 | D88: Defined | E88: 2 | F88: The Developed and Approved External Data Sharing Agreement Template. | G88: The Entity must attach the external Data Sharing Agreements with other Entities including the following, as a minimum: • The Purpose of Data Sharing. • Information about each requesting and sharing Entity. • Lawful / Legal / Regulatory basis for Sharing. • Sharing details (Date, Duration, etc.). • Liability provisions. • The Data Sharing Agreements signed by the Business Data Executive and the Requestor. | H88: P1 | I88: DSI.7.2 | J88: DSI.C.7.2.1 | K88: No | L88: No | M88: 1 | P88: Data Governance & Protection
A89: Data Sharing and Interoperability | B89: DSI | C89: DSI.MQ.2 | D89: Activated | E89: 3 | F89: Evidences of Operationalization of The Data Sharing Process, e.g.: Communication of The Defined Data Sharing Mechanism. | G89: The Entity must attach a communication operationalization report related to the defined mechanism of the Data Sharing process, including the following, as a minimum: • Correspondence exchanged proving the establishment of a communication channel between the communicating Entities. • A communication evidence of the approval of a formal mechanism defined for Data Sharing. | H89: P1 | I89: DSI.5.1 | J89: DSI.C.5.1.2 | K89: Under Development | L89: No | M89: 1 | P89: Data Governance & Protection
A90: Data Sharing and Interoperability | B90: DSI | C90: DSI.MQ.2 | D90: Activated | E90: 3 | F90: Evidences of Data Sharing Through SDAIA's Certified and Approved Channels. | G90: The Entity must attach a report on the electronic communication with the requestor Entity requesting Data Sharing through the SDAIA certified and SDAIA approved channels (e.g.: The Government Service Bus (GSB), etc.). The report may contain: • System screenshots or records. (The communication channel usage can include Data Sharing). • A report on the communications using the Entity’s formal government website. | H90: N/A | I90: N/A | J90: DSI.M.11 | K90: N/A | L90: No | P90: Data Governance & Protection
A91: Data Sharing and Interoperability | B91: DSI | C91: DSI.MQ.2 | D91: Activated | E91: 3 | F91: The Access Authorization Controls Document. | G91: The entity must attach a document detailing the Controls for authorization & usage when accessing the official government website channel for receiving requests. | H91: N/A | I91: N/A | J91: DSI.M.12 | K91: N/A | L91: No | P91: Data Governance & Protection
A92: Data Sharing and Interoperability | B92: DSI | C92: DSI.MQ.2 | D92: Activated | E92: 3 | F92: Evidences of Data Sharing Requests Submitted to The Entity and The Requests Submitted by The Entity Through the Established Channel. | G92: The Entity must attach the record(s) containing the Data Sharing requests: • The list received by the Entity. • The list sent / submitted by the Entity. | H92: P1 | I92: DSI.6.1 | J92: DSI.C.6.1 | K92: Under Development | L92: Partially | N92: Data has been shared and recived as per the attached letter, however there is no tracking list being conducted | O92: GACA Forecast Data Request - Letter (DSI.MQ.4) | P92: Data Governance & Protection
A93: Data Sharing and Interoperability | B93: DSI | C93: DSI.MQ.2 | D93: Activated | E93: 3 | F93: Evidences of the Entity's Responses to the Data Sharing Requests. | G93: The Entity must attach the notifications acknowledging receiving the Data Sharing requests with the responses. | H93: N/A | I93: N/A | J93: DSI.M.13 | K93: N/A | L93: No | P93: Data Governance & Protection
A94: Data Sharing and Interoperability | B94: DSI | C94: DSI.MQ.2 | D94: Activated | E94: 3 | F94: An Adoption Evidence of The Developed Data Sharing Agreement Template for An Internal Data Sharing Request. | G94: The Entity must attach a report containing an evidence of the Entity's adoption of a template developed for the Data Sharing Agreement upon an internal request from within the Entity. | H94: P2 | I94: DSI.7.1 | J94: DSI.C.7.1.2 | K94: No | L94: No | M94: 1 | P94: Data Governance & Protection
A95: Data Sharing and Interoperability | B95: DSI | C95: DSI.MQ.2 | D95: Activated | E95: 3 | F95: An Adoption Evidence of The Developed Data Sharing Agreement Template for An External Data Sharing Request. | G95: The Entity must attach a report containing an evidence of the Entity's adoption of a template developed for the Data Sharing Agreement upon a request from an external Entity. | H95: P1 | I95: DSI.7.2 | J95: DSI.C.7.2.2 | K95: No | L95: No | M95: 1 | P95: Data Governance & Protection
A96: Data Sharing and Interoperability | B96: DSI | C96: DSI.MQ.2 | D96: Activated | E96: 3 | F96: The Documented Review Outcomes of The Data Sharing Agreements. | G96: The Entity must attach a report on the results and outcomes of the documented reviews of the Data Sharing Agreements. | H96: P2 | I96: DSI.7.3 | J96: DSI.C.7.3 | K96: No | L96: No | P96: Data Governance & Protection
A97: Data Sharing and Interoperability | B97: DSI | C97: DSI.MQ.2 | D97: Managed | E97: 4 | F97: The Monitoring Report with Pre-defined KPIs for the Data Sharing Processes. | G97: The entity must attach an updated report approved by the entity’s authority holder on monitoring the effectiveness of the data sharing processes implementation based on pre_x0002_defined KPIs (Indicator Cards), covering: • The number of Data Sharing requests received. • The number of Data Sharing requests accepted / denied. • The number of Data Sharing requests sent. • The number of ongoing Data Sharing agreements. • The average duration of the Data Sharing request evaluation process expressed, in days. Each indicator’s data or card should include the following, as a minimum: • Indicator’s Name / Code. • Indicator’s Owner. • Indicator’s Coordinator. • Indicator’s Description. • The strategic / operational objective to be measured (with identifying the Specification or the Process to which the indicator belongs). • Indicator’s Equation. • Measurement Unit (Percentage, Number / Quantity, etc.). • Baseline (Measurement value in the first measurement year). • Target value. • Measurement Periodicity (Monthly / Quarterly / Biannually / Annually). • Data sources used to calculate the indicator. • Data collection mechanism. • Indicator’s polarity (+/-) (Positive Polarity: Higher indicator value is the target, Negative Polarity: Lower indicator value is the target). • The current value of the indicator compared to the target value. • The status of the indicator (achieved/delayed/not achieved/etc). The report should also include: • Recommendations for performance improvement based on the actual values of the indicators. • Supporting documents for the data used to calculate the indicator values. | H97: P2 | I97: DSI.8.1 | J97: DSI.8.1.1 | K97: No | L97: No | M97: 1 | P97: Data Governance & Protection
A98: Data Sharing and Interoperability | B98: DSI | C98: DSI.MQ.2 | D98: Managed | E98: 4 | F98: The compliance audit methodology. | G98: The Entity must attach the Compliance Audit Methodology document. | H98: N/A | I98: N/A | J98: DSI.M.14 | K98: N/A | L98: No | P98: Data Governance & Protection
A99: Data Sharing and Interoperability | B99: DSI | C99: DSI.MQ.2 | D99: Pioneer | E99: 5 | F99: The Continuous Improvement Report on the DSI Processes. | G99: The entity must attach the continuous improvement report of the Data Sharing Processes implementation, based on the results of the KPI measurements and relevant updates and developments in the domain containing the following, at a minimum:  Evidence of DSI Process automation.  The documents of the periodic reviews, evaluations & documented results of the DSI Domain Processes.  Improvements implemented (with supporting documents) | H99: N/A | I99: N/A | J99: DSI.M.15 | K99: N/A | L99: No | P99: Data Governance & Protection
A100: Data Sharing and Interoperability | B100: DSI | C100: DSI.MQ.3 | D100: Establishing | E100: 1 | F100: Evidences of Data Movement / Integration within the Entity and with Other Entities. | G100: The Entity must attach evidences of Data Movement or Data Integration / Interoperability: • Internally within the Entity. • Externally with other Entities. | H100: N/A | I100: N/A | J100: DSI.M.16 | K100: N/A | L100: Yes | O100: Integration_assessment, SANS Data Achitecture Assessment v1.0 | P100: Data Governance & Protection
A101: Data Sharing and Interoperability | B101: DSI | C101: DSI.MQ.3 | D101: Defined | E101: 2 | F101: The Integration Requirements Document. | G101: The Entity must attach the Integration / Interoperability Requirements document containing the following, as a minimum: • A clearly defined scope. • Entity's Business goals / objectives and aims to be achieved. • Implementation Timeline. • Resources required. • Cost estimate. • Functional requirements. • Non-Functional requirements. | H101: P1 | I101: DSI.3.1 | J101: DSI.C.3.1 | K101: Yes | L101: Yes | O101: ICD_Diplomatic Clearance System (DCS) (DSI.MQ.3), SANS-RAC-ICD-AODB-FDS V0.1- 05 Nov 2023 (DSI.MQ.3) | P101: Information Technology Data Management
A102: Data Sharing and Interoperability | B102: DSI | C102: DSI.MQ.3 | D102: Defined | E102: 2 | F102: The Solution Design Document. | G102: The Entity must attach the Solution Design document including the following, as a minimum: • Integration Solution Overview. • Target Data Integration Architecture. • Data Orchestration – The Data Flow Diagram (DFD). • Source to Target Mapping – A set of Data Transformation instructions that determine how to convert the structure and content of Data in the source system to the structure and content needed in the target system. The instructions shall include the following, as a minimum: ◦ The technical format of Data at the source and the target. ◦ The Specifications of transformations required for all intermediate staging points between the source and the target. | H102: P1 | I102: DSI.3.2 | J102: DSI.C.3.2 | K102: No | L102: No | N102: The provided evidence does not align with NDI requirements. (e.g. source to target mapping, data flows.are missing) | O102: ICD_Diplomatic Clearance System (DCS) (DSI.MQ.3), SANS-RAC-ICD-AODB-FDS V0.1- 05 Nov 2023 (DSI.MQ.3) | P102: Information Technology Data Management
A103: Data Sharing and Interoperability | B103: DSI | C103: DSI.MQ.3 | D103: Activated | E103: 3 | F103: The Document of the Approved Standardized Entity Wide Integration Solution Development Lifecycle. | G103: The entity must attach a life cycle description document, being the standardized and approved cycle for the development of Integration/Interoperability solutions at the entity level. The description should include the stages of the lifecycle for developing Integration/Interoperability solutions, roles and responsibilities, as well as practices implemented during the lifecycle of solution development. | H103: N/A | I103: N/A | J103: DSI.M.17 | K103: N/A | L103: No | P103: Information Technology Data Management
...

Sheet Maturity Questions Overview
B2: Maturity Questions
B3: Domain | C3: ID | D3: Question | E3: Maturity Level | K3: Maturity Level per Question
E4: Level 0 | F4: Level 1 | G4: Level 2 | H4: Level 3 | I4: Level 4 | J4: Level 5
E5: Absence of Capabilities | F5: Establishing | G5: Defined | H5: Activated | I5: Managed | J5: Pioneer
B6: Data Governance | C6: DG.MQ.1 | D6: Has the Entity established & implemented a Data Management & Personal Data Protection (DM & PDP) Strategy and a DM & PDP Plan with Key Performance Indicators (KPIs) that can be continuously measured to ensure optimization? | E6: No Data Management & Personal Data Protection (DM & PDP) strategy is in place. | F6: The Entity has existing DM practices that are not formalized (not approved). | G6: • A cross-Entity DM & PDP strategy is defined for all DM Domains. • DM Guiding principles have been developed. | H6: • The Entity developed a DM & PDP plan based on the defined DM & PDP strategy. • The Entity is implementing this DM & PDP plan which covers all DM Domains. | I6: The Entity is monitoring the DM & PDP strategy & plan implementation across all DM Domains with the pre-defined KPIs. | J6: • The DM & PDP strategy is periodically updated, improved and optimized across all DM Domains. • The DM & PDP implementation plan is periodically reviewed and updated based on both the changes to the DM & PDP strategy and the changing business requirements. | K6: =VLOOKUP(C6, Calculation!$T$3:$AA$45,8,FALSE) -> 2
C7: DG.MQ.2 | D7: Has the Entity established and implemented Data Management (DM) Policies, Standards and Guidelines across all Data Management (DM) Domains? | E7: No Data Management (DM) Policies, Standards or Guidelines are in place. | F7: • The Entity has existing DM-related policies and standards that are not formalized. • The Entity conducted a gap analysis to identify the required DM and PDP policies to be developed | G7: The Entity developed policies, standards and guidelines for all DM Domains. | H7: The Entity is implementing the developed DM and PDP policies with defined processes and standards to establish governance, uniformity and manage compliance across the Entity. | I7: • The DM and PDP policies, standards and processes are tracked and measured based on the pre-defined KPIs. • Periodic monitoring is conducted on the Entity's compliance with the Regulations published by NDMO-SDAIA. | J7: The DM and PDP policies, standards, DG processes and compliance with regulations are continuously reviewed and optimized. | K7: =VLOOKUP(C7, Calculation!$T$3:$AA$45,8,FALSE) -> 1
C8: DG.MQ.3 | D8: Has the Entity established and operationalized all roles required for the Data Management Organization as per the NDMO Controls & Specifications? | E8: No formal/approved Data Management Organization structure is in place. | F8: The Entity established a Data Management Office with one or two roles only. | G8: The Entity "Data Management & Data Governance Committee" (An internal executive committee) is established with a total of six roles (out of the DM Office roles) assigned & operationalized for the Data Management Organization. | H8: • All DM roles are established as per the DM and PDP Standards and fully adopted across the Entity. • Data Stewardship / Ownership defined across the Entity, in addition to providing business and technical support for critical Data systems & critical Data elements. | I8: • The Data Management Organization & the structure are fully established and operationalized. • The roles are tracked through pre-defined KPIs, periodically updated and optimized. | J8: Data Management Organization (& its structure) and Data stewardship (& its structure) (Data owners, business and technical stewards) are periodically reviewed and updated. | K8: =VLOOKUP(C8, Calculation!$T$3:$AA$45,8,FALSE) -> 0
C9: DG.MQ.4 | D9: Has the Entity established and implemented practices for Change Management including awareness, communication, change control, and capability development? | E9: No formal Change Management practices are in place. | F9: • Awareness sessions, training courses and communication on DM-related practices are performed on a reactive and ad-hoc basis. • The Entity has change control practices that are not formalized. | G9: • The Entity has defined Change Management practices. • There is an Entity-wide awareness, training and communication plan. • Change control practices are established to ensure coordinated efforts in managing changes on Data systems (implemented within the Entity). | H9: • The Entity is implementing the defined Change Management practices for all DM Domains. • Formal communication channels are established and adopted for DM issues management, escalations, resolutions & approvals. • A Version control mechanism is defined and implemented for DM documents and artifacts that the Entity published. • The DM & PDP Strategy is being socialized and awareness is conducted across the Entity. | I9: The Entity is monitoring the progress and the effectiveness of the Change Management practices with pre-defined KPIs. | J9: Change Management practices for all DM Domains are periodically reviewed, and continuously updated, optimized & developed. | K9: =VLOOKUP(C9, Calculation!$T$3:$AA$45,8,FALSE) -> 0
B10: Metadata & Data Catalog | C10: MCM.MQ.1 | D10: Has the Entity developed and implemented a plan to integrate and manage Metadata across the Entity? | E10: No plan is in place to integrate and manage Metadata in the Entity. | F10: The Entity manages its Metadata on a reactive and ad hoc basis. | G10: • The Entity developed a plan, an operating model and a structure for the implementation of Metadata and Data Catalog. • The Metadata management structure should include the requirements to capture, integrate, populate, publish and utilize the required technology solution for the Entity's Metadata (business and technical). • A roadmap is defined with a list of activities, required resources, and a budget to manage the Data Catalog and Metadata implementation. | H10: • The Entity is implementing the defined Metadata and Data Catalog plan and framework. • This implementation includes the identification and prioritization of the critical systems and attributes. | I10: The Entity is monitoring the effectiveness of the Metadata and Data Catalog plan and activities with pre-defined Key Performance Indicators (KPIs). | J10: The Metadata and Data Catalog plan and activities are regularly monitored for continuous improvement and optimization. | K10: =VLOOKUP(C10, Calculation!$T$3:$AA$45,8,FALSE) -> 0
C11: MCM.MQ.2 | D11: Has the Entity implemented a Metadata Management and Data Catalog tool / solution? | E11: No tools are in place to manage the Entity's Metadata. | F11: The Entity manages its Metadata manually or in standalone applications without standardized tools. | G11: • The Entity documented its requirements for the Data Catalog tool / solution and selected an appropriate tool based on business and regulatory requirements. • The Entity's data sources to be included in the Data Catalog tool have been identified and prioritized. • The Entity developed a target Metadata architecture. | H11: • The Data Catalog tool has been implemented and populated with the Entity’s Metadata. • The tool is integrated into the Entity’s Metadata repository with appropriate access permissions. • The tool stores the activities and tracking logs for Audit Trails. • Power users are identified and trained on the Data Catalog tool usage. • A training and communication plan is rolled out to raise awareness and adoption of the Data Catalog tool. • The Data catalog automated tool is regularly updated to the latest version. | I11: • The Entity is monitoring changes to its Metadata through automated notifications. • The adoption and usage of the implemented Data Catalog tool is closely monitored based on a set of pre-defined Key Performance Indicators (KPIs). | J11: • The Entity has fully automated end-to-end Metadata (Business, Technical, and Operational) capture and exchange. • The Entity continuously monitors and optimizes the Data Catalog. • The Entity continuously updates the Data Catalog in the event of any changes specified by the National Data Bank (NDB). | K11: =VLOOKUP(C11, Calculation!$T$3:$AA$45,8,FALSE) -> 0
C12: MCM.MQ.3 | D12: Has the Entity defined and implemented formal processes for effective Metadata Management, such as: prioritization, population, access management, and quality issue management, etc., supported & fostered by collaboration across the Entity? | E12: No process is in place to manage Metadata. | F12: The Entity manages the Metadata on a reactive and ad hoc basis (e.g. Projects / initiatives) without formalized practices. | G12: • The Entity defined processes to manage the Metadata across the business and technical applications. • The Entity developed processes to prioritize, populate and manage the Metadata including access management, annotation, certification, and Metadata quality; by collaboration across the Entity. | H12: • The Entity is implementing defined processes for end-to-end Metadata management. • The established processes for updating the Metadata are implemented and automated as workflows within the Data Catalog tool. • The Integrated Metamodel is deployed with role-based access. • The Metadata quality issues are identified and addressed. • Full end-to-end Metadata is collected and enriched. • All the Data Governance and Data Management teams along with business stakeholders are engaged collaboratively through the automated tool. | I12: The Entity is monitoring and tracking the Metadata processes and activities with pre-defined Key Performance Indicators (KPIs). | J12: • The Entity's Metadata management processes and practices are regularly monitored for continuous improvement and optimization. • Optimization techniques are being utilized to improve the processes of developing taxonomies, ontologies, or semantic representations. | K12: =VLOOKUP(C12, Calculation!$T$3:$AA$45,8,FALSE) -> 0
B13: Data Quality | C13: DQ.MQ.1 | D13: Has the Entity developed and implemented a Data Quality (DQ) plan focused on improving the quality of the Entity's Data? | E13: No formal Data Quality (DQ) plan is in place. | F13: The Entity implements Data Quality activities on a reactive or ad hoc basis. | G13: • The Entity has a defined and approved DQ management plan. • A roadmap is defined with a list of activities, required resources, and a budget to manage the DQ implementation. | H13: • The Entity is implementing the defined DQ plan and roadmap. • Clear roles and responsibilities are defined for the DQ activities in line with the Data Management Organization structure. | I13: The Entity is monitoring the implementation of the DQ plan and activities with the pre-defined Key Performance Indicators (KPIs). | J13: • The DQ plan and activities are regularly monitored for optimization and continuous improvement. • DQ Management is embedded in the Data Lifecycle and Software Development Lifecycle (SDLC). | K13: =VLOOKUP(C13, Calculation!$T$3:$AA$45,8,FALSE) -> 2
C14: DQ.MQ.2 | D14: Has the Entity established / developed and implemented practices to manage and improve the quality of the Entity's Data? | E14: No practices are in place for Data Quality (DQ). | F14: • The Entity has existing DQ-related practices that are not formalized. • The identification of Data issues and the resolution activities are done on a reactive or ad hoc basis. | G14: • The Entity prioritized Data elements based on the business requirements from the perspective of its importance for the DQ Management. • The Entity defined DQ Dimensions for the prioritized Datasets. • The Entity defined and documented DQ Rules including formats, mandatory fields, validations for Data-entry values. • The Entity established DQ issue management processes to identify and resolve the DQ issues. | H14: • The Entity is implementing DQ Management. • An initial DQ assessment was conducted to identify DQ issues. Periodic DQ assessments are established to ensure the improvement on the Entity's DQ. • Data issues were identified, a root cause analysis was conducted and remediation activities were developed accordingly to correct the identified Data issues. • Standardized DQ Tools are implemented with automated workflows and defined DQ Rules. | I14: • The Entity is monitoring the effectiveness of the DQ management practices with pre-defined KPIs. • The Entity is monitoring the agreed upon DQ threshold values with pre-defined SLAs. • The Entity is monitoring the effectiveness of the issue resolution process. | J14: • Proactive profiling and critical Dataset identification are done using Advanced Artificial Intelligence / Machine Learning (AI/ML) based methods. • The DQ tools are continuously optimized to improve the DQ management processes. • Proactive remediation is done with proper monitoring of critical Data systems, Data entities (Data objects) and Data attributes. • The Entity implemented DQ Management industry standards or developed Entity-specific standards. | K14: =VLOOKUP(C14, Calculation!$T$3:$AA$45,8,FALSE) -> 0
C15: DQ.MQ.3 | D15: Has the Entity established and implemented practices to monitor and report the Entity's Data Quality (DQ) status? | E15: No practices are in place to monitor nor report on the quality of Data. | F15: The Entity monitors its DQ on a reactive or ad hoc basis. | G15: • The Entity defined and formalized DQ monitoring and reporting practices to maintain and document the DQ activities on a regular basis. • The Entity developed DQ processes and a plan for conducting DQ Audits at defined checkpoints. | H15: • The Entity is monitoring the quality of its Data and documenting the quality status on a regular basis. • DQ reviews are conducted at the defined DQ Checkpoints. • A workflow for reporting DQ issues has been implemented on the Data Catalog automated tool. • The DQ Rules and the DQ Monitoring results are documented as the Metadata within the Data Catalog automated tool. | I15: The Entity monitors the DQ trends and reporting activities based on pre-defined KPIs and established targets. | J15: The Entity conducts periodic reviews of the monitoring and reporting practices for continuous improvement in line with the changes in business and technical requirements. | K15: =VLOOKUP(C15, Calculation!$T$3:$AA$45,8,FALSE) -> 0
C16: DQ.MQ.4 | D16: Has the Entity developed Data Quality (DQ) standards, provided definitions for its Datasets, and published / uploaded the definitions on the National Data Catalog (NDC)? | E16: No standards nor definitions are in place for the Entity's Datasets. | F16: The Entity defines its Datasets and DQ standards on an ad hoc / project basis. | G16: • The Entity has Data definitions and standards for a set of domains / attributes in line with the DQ Dimensions. • The Entity identified and provided Metadata definitions for all Data attributes in line with the DQ definitions. • The Entity identified the Datasets for which Metadata should be published on the National Data Catalog (NDC). | H16: • The Entity has been on boarded on the NDC. The Entity populated the Metadata definitions on the NDC. • The Entity is developing and implementing standards independently for the Entity-specific domains / attributes. • The Entity uploads the Metadata on the NDC as required. | I16: The Entity's Data definitions and Data standardization processes are reviewed and tracked through pre-defined KPIs. | J16: • The standards are developed proactively for all the new and future systems. The standards are continuously improved across the Entity's Data systems. • Regular assessments are conducted to ensure that the standards and definitions are provided and implemented for the Entity's Datasets. | K16: =VLOOKUP(C16, Calculation!$T$3:$AA$45,8,FALSE) -> 0
B17: Data Operations | C17: DO.MQ.1 | D17: Has the Entity developed and implemented a plan to manage and satisfy the needs of Data Operations, Data storage and Data retention? | E17: No plan is in place for Data Operations (DO), Data storage, Data retention and disaster recovery (DR). | F17: The Entity has existing practices for Data Operations, storage and retention. However, this plan is setup in a reactive form on an ad hoc basis. | G17: • The Entity has a defined and approved Data Operations (DO) and storage plan and roadmap including: 1- Data storage forecasting. 2- Budget and resource allocation. 3- Information systems prioritization. • This DO plan is in line with: 1- The policy development. 2- Tool selection. 3- Business continuity. • Plans for backup and disaster recovery. | H17: • The Entity is implementing its defined Data Operations (DO) plan. • The Entity assigned & activated the roles and responsibilities to manage the DO, storage and retention in line with the business requirements and the overall "Data Management Organization" structure. • The Entity is reporting on the Database performance. • The Entity is conducting periodic forecasts of its storage capacity. | I17: The Entity is monitoring the progress and effectiveness of the Data Operations (DO) plan implementation with pre-defined Key Performance Indicators (KPIs). | J17: The Entity's Data Operations (DO), storage, retention and recovery practices are continuously reviewed and optimized. | K17: =VLOOKUP(C17, Calculation!$T$3:$AA$45,8,FALSE) -> 1
C18: DO.MQ.2 | D18: Does the Entity have in place a defined methodology, processes and Standard Operating Procedures (SOPs) for Database operations? | E18: No practices nor processes are in place for Database management and operations. | F18: • The Entity conducts Data Operations but not in a standardized approach. • Operations are being managed without clear procedures or with minimal documented procedures. | G18: • The Entity has defined and developed practices and processes for Database operations management, monitoring and storage configurations including access control processes for the Databases. • All roles and support levels are identified to manage the Database Operations. • Processes and Standard Operating Procedures (SOPs) are documented with clearly defined roles and responsibilities across the operations and the IT teams. • The Database Management System (DBMS) / tool is regularly updated to the latest version. • Service Level Agreements (SLAs) are developed to guide the Database operations. | H18: • The Entity is implementing the defined Practices and Processes of Database operations management and Storage Configurations. • Under these Processes within the Entity, there are Standard Operating Procedures (SOPs) include: 1- The Database performance monitoring and reporting. 2- Role-based access control. 3- Storage Configuration Management and DBMS versioning (Implementation of Database changes on the Production Environments). • The Standard Operating Procedures (SOPs) are activated: 1- For all support levels, communication, escalation & resolution. 2- With all the involved stakeholders. • All required Data Operations (DO) roles are activated and onboarded. • The Service Level Agreements (SLAs) and the Operational Level Agreements (OLAs) are enforced as agreed upon with business stakeholders. | I18: Entity is monitoring the DO processes and SOP with pre_x0002_defined Key Performance Indicators (KPIs) and thresholds. | J18: • DO and Storage practices and processes are continuously reviewed and optimized. • Leading DO practices are evaluated on a regular basis and adopted (e.g., DataOps). • All operational metrics covering SLAs / OLAs, and Key Performance Indicators (KPIs) / Key Quality Indicators (KQIs) are reviewed proactively to improve and optimize the operations. • Proactive / preventive measures are planned and executed to ensure uninterrupted operations. • All learning scenarios and experiences cases are documented and updated regularly to create a knowledgebase for reusability and future planning. | K18: =VLOOKUP(C18, Calculation!$T$3:$AA$45,8,FALSE) -> 1
C19: DO.MQ.3 | D19: Does the Entity have in place, practices and processes for Business Continuity such as backup and disaster recovery (DR) and a defined Business Continuity Plan (BCP) for the Data? | E19: No plans, practices or processes are in place for business continuity such as backups and disaster recovery. | F19: The Entity's Data backup and disaster recovery practices are reactive and on an ad hoc basis. | G19: • The Entity has defined and developed plans, practices and processes for business continuity, Data backup, and disaster recovery in line with the DM and PDP standards. • The Recovery Time Objective (RTO) and the Recovery Point Objective (RPO) for the critical systems are defined (e.g., backup frequency, location of backup files, storage medium and scope). | H19: • The Entity is implementing its defined Business Continuity Plan (BCP), practices and processes for business continuity, Data backup and recovery. • The BCP is implemented for the critical systems. • Role-based access control for production data, all RTO / RPO details (High availability, load balancing, etc.) are agreed upon with Business and IT stakeholders and implemented. • The Incident response teams are activated. | I19: The entity is monitoring the practices pertaining to the BCP and DR with pre-defined Key Performance Indicators (KPIs). | J19: • The Entity continuously reviews Data storage backup & recovery and disaster recovery processes for improvement and optimization. • The Entity performs periodic executions and validations of the RTO and RPO to ensure that the systems are well prepared for any unexpected interruption or calamity. • The BCP details are regularly reviewed to incorporate the learnings, modern trends and business needs / demands. | K19: =VLOOKUP(C19, Calculation!$T$3:$AA$45,8,FALSE) -> 1
B20: Document & Content Management | C20: DCM.MQ.1 | D20: Has the Entity developed a Document and Content Management (DCM) plan and a Digitization plan to manage the implementation of paperless management activities? | E20: The Entity doesn’t have any plan in place currently for Document and Content Management (DCM). | F20: The Entity manages documents and content on a reactive or ad hoc basis without formalized DCM practices. | G20: • The Entity has defined plans to manage the Entity's documents and content lifecycle and digitization activities. A roadmap has been defined with a list of activities, required resources, trainings, awareness and a budget to manage both DCM and Digitization. • The Entity has defined processes for prioritizing and digitizing documents to be stored in the Entity's Document Management System (DMS). • The Entity has identified and prioritized the key processes to be implemented as workflows in DMS to enable automated and paperless management of documents. | H20: • The Entity is implementing its DCM plan and Digitization plan including training and awareness activities. • The Entity is prioritizing its documents to be stored in the Entity's Document Management System (DMS). • Roles and responsibilities are defined and initiated to manage the DCM activities and the Digitization activities in line with the overall "Data Management Organization" structure. | I20: The Entity is monitoring the effectiveness of the DCM plan and the DCM Digitization plan with pre-defined Key Performance Indicators (KPIs). | J20: The Entity continuously reviews and updates both its DCM plan and Digitization plan for improvement and optimization in line with the changing business needs. | K20: =VLOOKUP(C20, Calculation!$T$3:$AA$45,8,FALSE) -> 1
C21: DCM.MQ.2 | D21: Has the Entity implemented policies and processes for Document and Content Management (DCM) including: Backup & Recovery, Retention & Disposal, Document & Content Access Approval, and Metadata Publishing? | E21: No policies and processes are in place currently for Document and Content Management (DCM). | F21: The Entity manages its documents and content on a reactive and ad hoc basis without formalized DCM policies and processes. | G21: • The Entity defined a clear set of policies and processes to manage its documents and content. • The Processes are defined for: 1- Backup & Recovery. 2- Retention & Disposal. 3- Document and Content Access Approvals. 4- Metadata Publishing. | H21: • The Entity is implementing its DCM processes aligned with the policies. • The Document Management System (DMS) is included in the Entity's Backup & Recovery plan. • Documents are transferred to the Entity's archival facility (Archival Register). • The physical destruction and deletion of the documents is done securely. • The Entity established role-based access authorizations to the Content Management System (CMS) and the Document Management System (DMS). • Document and content Metadata is published via an automated tool. • Periodic DCM audits are conducted to ensure that the right information is getting to the right people at the right time. | I21: • The Entity is monitoring the DCM processes aligned with the policies with predefined Key Performance Indicators (KPIs). • The Audit Trail / Audit Framework is tracked based on predefined Key Performance Indicators (KPIs). | J21: The Entity regularly reviews and updates its DCM processes for continuous improvement and optimization. | K21: =VLOOKUP(C21, Calculation!$T$3:$AA$45,8,FALSE) -> 1
C22: DCM.MQ.3 | D22: Has the Entity implemented a tool to support Document and Content Management (DCM) processes including Digitization Management implementation? | E22: No tools are in place currently for managing documents nor content. | F22: The Entity manages documents and content in disparate applications. | G22: The Entity identified and developed or acquired the required tool to support DCM. | H22: The Entity implemented the selected tool for Document and Content Management (DCM) which includes: 1- A Document Management System (DMS). 2- A Web Content Management System (CMS). 3- A collaboration tool. | I22: The Entity is monitoring the implementation of the tool based on pre-defined Key Performance Indicators (KPIs). | J22: For Continuous Improvement, the Entity regularly reviews: 1- The performance of the implemented Digitization Management tool to ensure automation. 2- The DCM activities to ensure optimization. | K22: =VLOOKUP(C22, Calculation!$T$3:$AA$45,8,FALSE) -> 2
B23: Data Architecture & Modelling | C23: DAM.MQ.1 | D23: Has the Entity developed and implemented a plan to improve its Data Architecture Capabilities? | E23: No plan is in place for Data Architecture & Modelling (DAM). | F23: The Entity manages its Data Architecture & Modelling (DAM) related activities on a reactive and ad hoc basis without formalized practices. | G23: • The Entity has a defined & approved DAM Management plan. • The Entity developed an Entity-wide baseline current state and target future state Data Architecture in accordance with the Enterprise Architecture (EA). • The Entity performed a gap analysis resulting in an implementation roadmap with defined priorities. • The Entity adopted a Standard enterprise architecture framework. • The Entity published its DAM Policies & Guidelines. | H23: • The Entity is implementing the defined implementation roadmap for its Target State Data Architecture. • The IT architecture is ensuring all business architecture outcomes are addressed by selecting and implementing the right technical capabilities. • The Business Architecture team works closely with the Entity's Enterprise Architecture team to align the applicable Standards (e.g., DMBOK, TOGAF, etc.). | I23: The Entity is monitoring the effectiveness of the DAM Plan & activities with pre-defined Key Performance Indicators (KPIs). | J23: • The Entity follows an identified architecture Change Management process to review, approve and implement the changes to the Current and / or Target State Data Architectures. • The Entity continuously reviews the Target State Data Architecture via checkpoints incorporated into the Software Development Lifecycle (SDLC) process. • The Entity regularly reviews and refines the Target State roadmap, priorities, and architecture artifacts, reflecting the current Enterprise Architecture strategy and key initiatives. | K23: =VLOOKUP(C23, Calculation!$T$3:$AA$45,8,FALSE) -> 0
C24: DAM.MQ.2 | D24: Has the Entity developed and implemented practices for Data Architecture & Modelling (DAM) activities (including Data Flows, Data Models and Governance considerations)? | E24: No practices are in place within the Entity for Data Architecture & Modelling (DAM). | F24: • The Entity maps Data Flows to the business processes only on a reactive basis for specific projects / initiatives. • Foundational Data Flows are identified, defined and designed but primarily driven by a project / an initiative. | G24: • The Entity has identified & defined the requirements for developing a Data Lake environment. • The Entity has defined a Partitioning Strategy for the target state data architecture. • The Entity identified and mapped its Data Flows to the business processes. • The Entity's Enterprise Data Model adopts a Standard diagramming method (e.g. UML) for documenting the structure, relationships and notations of business entities at the conceptual, logical and physical levels. • The Entity stores in a register, its Data & Technical Architecture projects, Reference documentation materials and Data Model designs. • The end-to-end Data Modelling lifecycle is defined with required processes and best practices / guidelines such as naming conventions, Data types, physical model deployment considerations and optimizations, etc. | H24: • The Entity is implementing the defined practices for its DAM activities. • Multiple Data integration and flow patterns are designed, published and are operating on defined Data architecture principles such as "Capture Once Use Many" etc. • Structured and streamlined information flows across the Entity are done using the defined and published Data integration patterns. • The Entity is implementing tools and technologies for DAM initiatives. • Data Models are uploaded in the Data Catalog. • The Logical Model is linked with business glossaries and technical attributes to provide end-to-end lineage and activate the impact analysis. • The Entity's Enterprise Data Model is used throughout the Software Development Lifecycle (SDLC). • The development is done via a Data Model tool. | I24: The Entity is monitoring the implementation of the DAM practices with pre-defined Key Performance Indicators (KPIs). | J24: • The mapping of the Entity's Data Flow to the Business processes is continuously monitored, measured, and improved including: • Multi-latency, multi-format Data Flows & Architecture Patterns defined, adopted, and mapped to the business processes. • Entity-wide Data structures and Data services mapped to the business processes. • Entity-wide Data structures and Data services shared in real-time. | K24: =VLOOKUP(C24, Calculation!$T$3:$AA$45,8,FALSE) -> 0
B25: Data Sharing & Interoperability | C25: DSI.MQ.1 | D25: Has the Entity developed and implemented a Data Sharing and Integration (DSI) Plan in line with the Data Sharing Policies? | E25: No plan is in place for Data Sharing nor Integration | F25: • The Entity shares Data on a reactive or ad hoc basis. • Manual Data exchange practices exist within the Entity and with other Entities. • A DSI practice and initial data integration assessment of the Entity's current state has been conducted to identify pain points and inefficiencies in the data transfer and the integration across the Entity. | G25: • A Target Data Integration Architecture was developed based on the identified pain points. • The Entity has developed an integration strategy and implementation plan for data sharing and integration to remediate the identified pain points and manage the required integration initiatives. • The Data Sharing policies and guidelines are defined for DSI within and outside the Entity in line with the Data Sharing Regulations published by NDMO-SDAIA. • The Entity has developed a plan for training every employee involved in the Data Sharing initiatives. | H25: • The Entity is implementing The defined plan and roadmap for Data sharing and integration. • Roles and responsibilities are assigned within The Entity to manage Data sharing requests and Data integration activities in line with both The Data Management Organization structure and The Data sharing regulations published by NDMO-SDAIA. • The Entity is conducting Data sharing training in line with The Data sharing training plan. | I25: The Entity is monitoring the implementation of the DSI activities to ensure completion as per the plan with pre-defined Key Performance Indicators (KPIs). | J25: The DSI plan and the activities are continuously optimized to facilitate innovation and to maintain compliance with the Data Sharing Policies | K25: =VLOOKUP(C25, Calculation!$T$3:$AA$45,8,FALSE) -> 0
C26: DSI.MQ.2 | D26: Has the Entity defined and implemented Processes for Sharing Data within the Entity and with other Entities? | E26: No processes are in place for sharing the Entity's Data internally nor externally. | F26: The Entity shares Data on a reactive or ad hoc basis within and outside the Entity with no formalized practices | G26: • The Entity defined and approved a standardized Data Sharing mechanism for sharing Data internally and externally according to the defined classification levels. The mechanism includes forms, processes and agreements to be used to manage the Data Sharing requests in line with the Data Sharing principles and regulation. • Data Sharing request forms have been developed and are shared with Data requestors as needed. • The Data Sharing agreements have been developed for Internal and External Data Sharing. | H26: • The Entity is implementing and operationalizing the defined and approved Data Sharing mechanism to facilitate Data Sharing within and outside the Entity. • Data is shared with Entities only through SDAIA's certified and approved channels (e.g., The Government Service Bus (GSB), National Information Center Network, etc.). • The Entity put in place controls to ensure that only the appropriate authority is allowed to access, obtain and use the shared Data based on the nature and sensitivity of the Data. • All ongoing Data Sharing agreements are reviewed on a regular basis to accommodate for any changes. • The Entity's official Government website has an established channel to manage Data Sharing requests. | I26: The entity is measuring the efficiency of Data Sharing activities, tracking progress, and ensuring compliance with pre-defined KPIs | J26: • The Entity's Data Sharing process is automated and updated frequently. • Data Sharing practices are regularly reviewed and adjusted to address the changing business objectives while implementing continuous improvements. • Data-as-a-service (DaaS) and Data products are developed and maintained proactively by the Entity. • DSI is fully automated and scalable with full control on protection and privacy at the Entity level. | K26: =VLOOKUP(C26, Calculation!$T$3:$AA$45,8,FALSE) -> 1
C27: DSI.MQ.3 | D27: Has the Entity defined and implemented a Data integration architecture to manage the Data movement efficiently across Data stores, systems, and applications? | E27: No practices in place to manage the Data movement across the entity's systems and applications | F27: The data movement across Data stores, systems, and applications is done on ad-hoc basis with no formal architecture | G27: • The Entity defines its business requirements for each initiative requiring data integration between Data stores, systems, and applications. • The Entity develops a solution design document for each data integration initiative based on the target data integration architecture and the Integration Requirements Document. | H27: • The Entity is implementing the Data integration architecture following an integration solution development lifecycle for each data integration initiative. • The entity performs testing of the developed integration solution before deployment to the production environment. • Data sources are integrated through established and approved integration patterns. | I27: The Entity is monitoring the effectiveness of the integration initiatives with pre-defined KPIs. | J27: The Entity reviews the integration architecture regularly and optimizes the integrations practices by adopting cutting edge methodologies (e.g., Implementing Continuous Integration and Continuous Deployment (CI/CD) pipelines) to automate and streamline the improvement of the integration solution | K27: =VLOOKUP(C27, Calculation!$T$3:$AA$45,8,FALSE) -> 1
C28: DSI.MQ.4 | D28: Has the Entity developed and implemented Data Sharing Controls and Processes for efficient Data transformation and movement? | E28: No controls or processes in place for data sharing or data transformation and movement | F28: The Entity implements controls for data sharing and moves data across applications on an ad-hoc basis without formalized controls or processes | G28: • The Entity has defined data sharing controls, processes and standards for Data transformation and Data movement across the Entity's applications. • The Entity has conducted a risk assessment of DSI processes. • The Entity has defined specific processes to classify, protect and support Data privacy. | H28: • The Entity is implementing defined processes for data transformation and movement (ETL/ELT), and controls for Data Sharing. This includes processes for integrating data from disparate sources and loading into Data Warehouse Store, and processes for storing unstructured data in its raw native format in the Data Lake. • The Entity is implementing standards for Data development, transformation and movement across all applications. • The Data security controls are implemented in line with the security controls published by the KSA's National Cybersecurity Authority (NCA). • Appropriate controls are applied on the Datasets to be shared in line with the Data Sharing regulations and other relevant regulations (e.g., Personal Data Protection (PDP) etc.). | I28: The Entity is monitoring the effectiveness of the DSI controls, processes and standards with pre-defined KPIs. | J28: • The Entity continuously reviews its Data sharing and integration controls and practices for optimization by adopting advanced interoperability standards (e.g., Event driven, event sourcing, Data mesh, etc.). • The transformed and merged Data is available upon request as a service (DaaS) for various transactions, reporting and analysis in the Entity for innovation (e.g., Data-driven transformation and products, etc.). • Proactive periodic audits and reviews of the applications and systems are performed in an automated way. | K28: =VLOOKUP(C28, Calculation!$T$3:$AA$45,8,FALSE) -> 1
B29: Reference & Master Data Management | C29: RMD.MQ.1 | D29: Has the Entity developed and implemented a plan focused on improving its Reference & Master Data (RMD) Management capabilities? | E29: The Entity doesn't have a plan in place for Reference & Master Data (RMD) Management | F29: The Entity manages its Reference & Master Data (RMD) on a reactive or ad hoc basis without formalized practices | G29: • The Entity has a defined and approved RMD Management plan. • A roadmap is defined with a list of activities, required resources, trainings and a budget to manage the RMD plan implementation. | H29: • The Entity is implementing the defined RMD Management plan and roadmap. • Clear roles and responsibilities are defined and activated for the RMD activities. • Business and IT Data stewards are assigned in line with the "Data Management Organization" structure. • Training is being conducted for all Entity's employees responsible for the management of its RMD as required in line with the change management practices. • The RMD change request logs and the decisions are documented. • The documented RMD Management initiatives registered in the statement of Architecture work are being implemented. | I29: The Entity is monitoring the effectiveness of the RMD Management plan and activities with pre-defined KPIs | J29: The Entity's RMD Management plan and activities are continuously reviewed and updated for optimization and improvement. | K29: =VLOOKUP(C29, Calculation!$T$3:$AA$45,8,FALSE) -> 2
C30: RMD.MQ.2 | D30: Has the Entity defined and implemented processes to manage its Reference & Master Data (RMD) objects from creation to archival? | E30: No processes are in place for Reference & Master Data (RMD) management | F30: The Entity manages its RMD on a reactive or ad hoc basis (e.g.: Projects / initiatives) without formalized practices | G30: • The Entity has defined processes to manage its RMD objects across the business and technical applications. • RMD requirements are documented in line with business needs. • RMD objects are identified, prioritized, and categorized (Internal or External). • Standards and rules for matching and merging Master Data Objects and Reference Datasets are defined. • Processes are developed for the RMD lifecycle (Creation, modification, and archiving). • Service Level Agreements (SLAs) are defined for the processes. | H30: • The Entity is implementing its RMD Management Processes. • Match and Merge, survivorship rules for Master Data Objects are embedded in the Data transformation rules and implemented on the Entity's Data applications. • Rules for standardized Reference Data are embedded in the Entity's Data applications and managed centrally. | I30: The Entity is monitoring the processes for managing the RMD Objects across the Data lifecycle with pre-defined KPIs | J30: The Entity's RMD Management Processes and Standards are continuously monitored for optimization and improvement | K30: =VLOOKUP(C30, Calculation!$T$3:$AA$45,8,FALSE) -> 0
C31: RMD.MQ.3 | D31: Has the Entity implemented a Data Hub (or Tool) as the trusted Data source to support the RMD Management Processes? | E31: No tools are in place for managing the Reference & Master Data (RMD). | F31: The Entity manages its RMD within standalone Data sources without standardized tools | G31: • The Entity identified The required Hub / Tool for RMD Management based on business and technical requirements. • a suitable Data Hub architecture implementation pattern is agreed upon and The Data Hub design is developed. • a conceptual and information architecture is developed based on The selected Data Hub architecture Design. • RMD models and architectures are developed. • RMD Hub / Tool technical requirements are documented based on The defined target RMD information Architecture. | H31: • The Entity implemented the selected Data Hub for RMD Management and is operating the hub as the Trusted Source of RMD across the Entity. • The implemented Data Hub is flexible to accommodate new Data sources and to support workflow capabilities and customizations (e.g., Data localization, privacy, consent management, hierarchy management, and exception processing and automated alert capabilities). | I31: The Entity is monitoring the adoption and usage of the implemented Data Hub with the pre-defined KPIs. | J31: The Entity continuously inspects the implemented Data Hub to: • Ensure full coverage of all new and updated Data sources. • Ensure that all deployed tools and technologies are regularly optimized. • Ensure that the level of automation increased based on industry and global trends. • A centralized Hub / Tool is developed being the Trusted Data Source wherein all the RMD Objects are hosted and maintained. | K31: =VLOOKUP(C31, Calculation!$T$3:$AA$45,8,FALSE) -> 0
B32: Business Intelligence & Analytics | C32: BIA.MQ.1 | D32: Has the Entity developed and implemented a plan to manage and orchestrate its Business Intelligence & Analytics (BIA) activities? | E32: No formal Business Intelligence & Analytics (BIA) plan is in place. | F32: The Entity implements BIA activities on a reactive or ad hoc basis. | G32: • The Entity has a defined and approved BIA plan based on the overall Data Management (DM) strategy. • A roadmap is defined with a list of activities, required resources and budget to manage the BIA implementation. | H32: • The Entity is implementing the defined & approved BIA plan & roadmap. • Clear roles and responsibilities are defined for the BIA activities in line with the Data Management Organization structure. | I32: The Entity is monitoring the effectiveness of the BIA plan and activities with pre-defined Key Performance Indicators (KPIs). | J32: The BIA plan and activities are continuously reviewed and updated for optimization and improvement. | K32: =VLOOKUP(C32, Calculation!$T$3:$AA$45,8,FALSE) -> 2
C33: BIA.MQ.2 | D33: Has the Entity identified BIA use cases and defined a plan for the use case implementation? | E33: No defined BIA use cases are identified within the Entity. | F33: The Entity identifies and implements BIA use cases on ad hoc basis or for specific projects and initiatives. | G33: • The Entity has identified and prioritized its BIA use cases using a defined prioritization framework. • Shortlisted use cases have been documented in a detailed BIA Use Case Portfolio document. • An Implementation plan has been developed for each shortlisted and approved use case with implementation priorities based on the Entity's defined use case implementation approach. • A use case validation process has been developed. | H33: • The Entity is implementing and validating The prioritized use cases in order to transform The Entity into a Data-driven organization. • The new use cases are evaluated and implemented based on The business requirements. • The implemented BIA use cases and their final outcomes are documented in a register. | I33: • The Entity is evaluating / monitoring the performance of analytical models and business impacts of implemented use cases with pre-defined Key Performance Indicators (KPIs). • The Technical or Business impacts and the Return on Investment (ROI) from the use cases are monitored with pre-defined KPIs. | J33: • The Entity's activated and implemented BIA use cases are regularly reviewed and optimized. • The potential impact, competitive advantage, Total Cost of Ownership (TCO) and Return on Investment (ROI) are continuously reviewed and updated with a defined calculation methodology. | K33: =VLOOKUP(C33, Calculation!$T$3:$AA$45,8,FALSE) -> 0
C34: BIA.MQ.3 | D34: Has the Entity defined and implemented practices to manage and govern the BIA processes? | E34: No practices are in place for BIA | F34: • The Entity manages its BIA processes on a reactive or ad hoc basis without formalized practices. • Reporting is done either on direct source systems; or different Data Marts are developed based on the business needs with no semantic relationship / link among them. • The BIA Governance focuses only on the requirements of the projects. • The DQ issues are resolved during the Data population for BI by the BI team. | G34: • The Entity has defined formal BIA practices including the development of processes for a Data warehouse or a Data Lake with logical models in place to model the business functions. • A Semantic layer is developed and maintained for supporting BI and Advanced Analytics use cases. • The Entity is developing a change management plan including training programs, awareness campaigns and a release management process to guide the publishing mechanism of reports, dashboards and implemented uses cases. | H34: • The Entity is implementing the defined BIA processes and practices which are established to govern BIA activities. • Self-service analytics are fully activated covering both BI & AI/ML. • Business users have full access to all types of Data (Raw, Processed, Modelled) in a governed manner. • End-to-end governance is in place covering emerging topics such as AI ethics, etc. • Advanced Analytics (AI/ML) governance and management (AI/ML OPs) foundational processes are in place operationally. • A central Data Science & BIA team has been set up with defined roles and responsibilities. • The central Data Science & BIA team has a clear process flow to handle the Entity's BIA needs. • BIA training courses are conducted for all employees involved in the BIA initiatives to upskill the analytics capabilities; and awareness campaigns are conducted to promote the awareness, education & adoption of the BIA capabilities. | I34: The Entity is monitoring BIA processes, governance and the performance of the centralized BI team with pre-defined Key Performance Indicators (KPIs). | J34: • The Entity created a BI Competency center including the required roles, skills & capabilities to fulfil all BI requirements. • The Entity created a BI Competency center which is governing the Entity's BI management including the demand management and change management. • The performance of the BIA team is continuously reviewed, measured and optimized. • The BIA Capacity planning is reviewed regularly and fulfilled to support the growing demand. | K34: =VLOOKUP(C34, Calculation!$T$3:$AA$45,8,FALSE) -> 0
C35: BIA.MQ.4 | D35: Has the Entity implemented the right tools, technologies, and skills to empower users and support the implementation of the BIA use cases? | E35: No technology for BIA is in place. The reporting is done Manually. | F35: The Entity implements its BIA activities on an ad hoc basis or individual applications without formalized tools | G35: • The Entity selected standardized tools to develop standard analytics artifacts (reports and dashboards). • The Business and IT stakeholders collaborate to develop, enhance and maintain the Semantic Layer. | H35: • The Entity selected and implemented tools and technologies that are being adopted across the Entity. • The Entity has self-service advanced analytics (Data discovery, wrangling, statistical analysis, etc.) and collaborative Artificial Intelligence / Machine Learning (AI / ML) using a low-code / no-code environment. • Users have the choice of a unified interface in their workflows by using: • Tools. • Programming Languages (e.g., Python, R, Go, etc.). • Platforms (e.g., Anaconda, Jupiter, etc.). • Libraries (e.g., Pandas, Numpy, etc.). • Project documentation is managed centrally and shared across the Entity. • Common AI / ML Models are versioned and documented through the tools. • Users have the ability to reuse those AI / ML Models in developing new BI Analytics & Models. | I35: The Entity is monitoring the adoption and utilization of the BIA tools and technologies with pre-defined Key Performance Indicators (KPIs). | J35: • New technologies are regularly evaluated, tested, and introduced to keep the capabilities aligned with the future needs. • Advanced frameworks are used (e.g., Spark, TensorFlow, PyTorch, etc.) and integrated with their unified AI/ML environment. • Advanced capabilities such AI/ML engineering tools and features are used for complex processing and reusability. • Tools and technologies which use AI/ML OPs are practiced to manage the end-to-end AI/ML lifecycle. | K35: =VLOOKUP(C35, Calculation!$T$3:$AA$45,8,FALSE) -> 1
B36: Data Value Realization | C36: DVR.MQ.1 | D36: Has the Entity developed a plan to identify, document and realize its Data revenue generation potential and implement Data-related cost optimization initiatives and use cases? | E36: • No plan is in place to generate value from Data nor implement Data-related cost optimization initiatives. • No use cases are identified for Data revenue generation nor Data-related cost optimization. | F36: The Entity has existing practices for Data Value Realization (DVR), Data-related cost optimization and identification of use cases, however, this is done in a reactive or ad hoc basis without formalized DVR practices. | G36: • The Entity has a defined and approved plan to identify, document and realize value from its Data through revenue generation initiatives and Data-related cost optimization initiatives. • The Entity identified use-cases for revenue generation and cost optimization based on the guidelines for ethical use cases. • The Entity estimated and projected a Payback period and Return on Investment (ROI) for each identified use case. • Roles and responsibilities to support the DVR implementation have been identified and documented. | H36: • The Entity is implementing its DVR plan through use-cases for revenue generation and cost optimization. • Roles and responsibilities for DVR use-case implementations are activated in line with the Data Management Organization structure. • The Entity is maintaining the DVR use cases. | I36: The Entity is monitoring the efficiency of the plan implementation and DVR activities with pre-defined Key Performance Indicators (KPIs) in line with the “DM and PDP Standards” document. | J36: The DVR plan implementation is regularly reviewed and optimized to ensure continuous improvement. | K36: =VLOOKUP(C36, Calculation!$T$3:$AA$45,8,FALSE) -> 0
C37: DVR.MQ.2 | D37: Has the Entity implemented practices to support a Data revenue generation process? | E37: No processes are in place for use cases of both: Data revenue generation and cost optimization. | F37: The Entity has not implemented a formalized process for Data revenue generation, however, this is done in a reactive or ad hoc basis. | G37: The Entity has a defined, documented, and approved process for Data revenue generation covering the details of: • The selection of a pricing schema model. • The calculation of the total cost. • Aligning the adopted charging model in line with the business needs. | H37: • The Entity is implementing the defined process of Data revenue generation. • For each Data revenue generation request, the Entity submits the required documentation to NDMO-SDAIA. • For each Data or Data Product that the Entity is expecting to generate revenue from, the Entity submits a revenue generation request to NDMO-SDAIA. | I37: The Entity is monitoring the efficiency of the Data revenue generation process with pre-defined KPIs. | J37: The Revenue Generation Process is regularly reviewed and optimized to ensure continuous improvement. | K37: =VLOOKUP(C37, Calculation!$T$3:$AA$45,8,FALSE) -> 0
B38: Open Data | C38: OD.MQ.1 | D38: Has the Entity defined, established, and implemented a plan to identify and coordinate the publishing of its Open Datasets? | E38: No Open Data (OD) plan is in place. | F38: The Entity has existing practices to maintain OD, but these practices are not formalized. | G38: • The Entity has defined an OD plan and framework. • OD Management structure is in place and a change management plan has been developed to conduct training on OD activities and awareness campaigns. | H38: • The Entity is implementing the activities on the defined Open Data plan including training & awareness programs. • An annual report on the Open Data plan & progress is submitted to NDMO-SDAIA. • The Entity appointed the following roles in line with the Data Management Organization: ◦ Open Data & Information Access Officer (ODIAO) to lead the Open Data activities within the Entity. ◦ Business Data Executive (BDE). ◦ Business Data Steward. | I38: The Entity is monitoring the effectiveness of the Open Data activities plan with pre-defined Key Performance Indicators (KPIs). | J38: The Open Data plan is revised & optimized for continuous improvement. | K38: =VLOOKUP(C38, Calculation!$T$3:$AA$45,8,FALSE) -> 0
C39: OD.MQ.2 | D39: Has the Entity defined, established, and implemented a process to support the identification of Open Data (OD)? | E39: No existing process is in place to identify Open Data (OD) within the Entity. | F39: Open Data identification practices are performed on a reactive or ad hoc basis, without formalized OD practices. | G39: • The Entity has developed and documented processes required to manage the lifecycle of Open Data. • In alignment with the Open Data Policy, the Entity defined a process to identify public Datasets to be published including a mechanism to evaluate all Data classified as “Public Data” to determine whether to be published as OD or not. | H39: • The Entity is implementing the defined processes for identifying the Datasets to be published. • The Entity is evaluating the identified datasets in terms of value whilst also conducting risk assessment to ensure there will be no security or privacy threats when published. • The Identified Open Datasets are being aligned with the regulations published by NDMO-SDAIA. • The Entity has identified & documented metadata of the Entity's open datasets. | I39: The Entity is monitoring the effectiveness of the implemented processes of identifying Open Datasets with pre-defined KPIs. | J39: The Entity is conducting continuous improvement, enabled by automated processes to support OD identification. | K39: =VLOOKUP(C39, Calculation!$T$3:$AA$45,8,FALSE) -> 0
C40: OD.MQ.3 | D40: Has the Entity defined, established, and implemented a process to support publishing its Open Datasets? | E40: No existing process are in place for managing Open Datasets within the Entity. | F40: Open Data (OD) is shared on a reactive or ad hoc basis. | G40: • The Entity has defined a process to manage the publishing of Open Datasets as part of the documented Open Data processes. • The Entity has defined a process to regularly review, update and document changes to its published Open Datasets and associated metadata to ensure they meet defined regulatory requirements. | H40: • The Entity is implementing the defined process for publishing Open Data by collaborating with National Information Center (NIC) in SDAIA to publish the Open Datasets on the Saudi Open Data Portal under the KSA Open Data License. • The Entity utilizes standardized formats when publishing its datasets that are in machine-readable form. • The Entity ensures that the open datasets are published in high quality to ensure fitness for use. • The Entity is updating the published open datasets and the associated Metadata and maintaining data traceability and versioning history of the open datasets. • The Entity is documenting in a register its identified open datasets and activities. | I40: The Entity is monitoring the effectiveness of the Open Data processes with pre-defined KPIs, covering: 1. The number of downloads per published Open Dataset. 2. The number of defined, identified and prioritized Open Datasets. 3. The number of identified Open Datasets that have been published. 4. The number of updates performed on published Open Datasets. | J40: • The Entity is conducting continuous improvement to support the defined OD publishing processes to ensure optimization. • The published Open Datasets and the associated Metadata are regularly reviewed and updated to the newest version. • The OD and the associated Metadata changes are documented where necessary. | K40: =VLOOKUP(C40, Calculation!$T$3:$AA$45,8,FALSE) -> 0
B41: Freedom of Information | C41: FOI.MQ.1 | D41: Has the Entity defined and established a plan to address its compliance with the requirements of the Freedom of Information (FOI) Regulations? | E41: No plan is in place to address the Freedom of Information (FOI) regulations within the Entity. | F41: The Entity has existing FOI practices in place to address its compliance with the FOI Regulations without formalized practices. | G41: • The Entity has a defined and approved FOI plan. • A roadmap is defined with a list of activities, required resources, training courses & awareness campaigns, and a budget to manage the FOI plan implementation. | H41: • The Entity is implementing the defined plan to manage FOI requests. • The Entity is publishing on its official Government website with a feedback mechanism for questions or issues raised. • The Entity appointed an Open Data & Information Access Officer (ODIAO) to manage the Entity's compliance with the FOI regulations in line with the "Data Management Organization" structure. • The Entity launched awareness campaigns to promote and enhance the culture of transparency and to raise awareness of the FOI regulations published by NDMO-SDAIA. | I41: • To comply with the FOI Regulations, the Entity is monitoring the effectiveness of the plan established with pre-defined Key Performance Indicators (KPIs). • The Entity is conducting periodic audit and review processes on the compliance with FOI regulations published by NDMO-SDAIA. | J41: The Entity's FOI plans and practices are continuously reviewed and optimized. | K41: =VLOOKUP(C41, Calculation!$T$3:$AA$45,8,FALSE) -> 0
C42: FOI.MQ.2 | D42: Has the Entity defined and implemented the required processes for Freedom of Information (FOI)? | E42: No existing practices are in place for Freedom of Information (FOI) within the Entity. | F42: The Entity responds to FOI requests on a reactive and ad hoc basis. | G42: • The Entity has defined processes to manage FOI requests (including response processes and appeal / denial processes) in alignment with the National Data Governance Regulations. • The Entity has developed end-to-end processes, steps and Frequently Asked questions (FAQs) for acquiring information from the official Gov portal / website. | H42: • The Entity is implementing the defined processes and practices for FOI Regulatory Compliance to ensure adoption across the Entity. • The Entity is publishing on the official portal / website, the end-to-end process guide and the FAQs required for acquiring the information. • An FOI Request Management process is activated across the Entity, including access and appeal / denial practices. • The Entity has a record keeping system which is regularly updated on the FOI Register. • The Entity adopted a pricing scheme for Public Information Access Requests. | I42: The Entity is monitoring the completeness and performance of the FOI processes with pre-defined KPIs. | J42: • The Entity continuously reviews & optimizes FOI processes & practices. • The FOI request responding process is automated. | K42: =VLOOKUP(C42, Calculation!$T$3:$AA$45,8,FALSE) -> 0
B43: Data Classification | C43: DC.MQ.1 | D43: Has the Entity established a plan for Data Classification (DC) as stipulated by the Data Management and personal Data protection (DM & PDP) standards? | E43: No plan for Data Classification (DC) is in place. | F43: The Entity has existing DC practices which are not formalized. | G43: The Entity defined a plan for DC to manage and orchestrate its DC activities. | H43: The Entity has implemented the defined DC plan and roadmap on all approved Datasets/artifacts. | I43: The Entity is monitoring the effectiveness of the DC plan & activities with the pre-defined Key Performance Indicators (KPIs). | J43: The DC plan & activities are continuously reviewed & updated for optimization & improvement. | K43: =VLOOKUP(C43, Calculation!$T$3:$AA$45,8,FALSE) -> 2
C44: DC.MQ.2 | D44: Has the Entity defined, identified and implemented the required Data Classification (DC) processes? | E44: No existing processes for Data Classification (DC) are in place within the Entity. | F44: Existing DC activities are performed on a reactive or ad hoc basis. | G44: • The Entity developed a prioritization framework to classify its Datasets. • The Entity developed a framework for conducting the impact assessment. • The Entity defined Data handling Data protection Controls for the Datasets and artifacts. • The Entity defined & identified the DC levels in line with the DM and PDP standards. • The Entity defined a process for identification and inventory of its Datasets and artifacts | H44: • The Entity is identifying and maintaining an inventory of all datasets and artifacts owned by the Entity. • The Entity is conducting prioritization based on the identified Datasets. • The Entity is conducting an impact analysis to assess any potential damage of unauthorized access to its identified Datasets and assigning the defined DC levels in line with the DM and PDP standards. • The Entity is conducting an impact analysis for data classified as low impact. • The Entity is implementing the defined Data Handling and Protection Controls based on the classification level for the Datasets/artifacts. • The Entity is assigning Data access rights and privileges across the Entity. • The Entity is maintaining a register of all identified datasets and artifacts. | I44: The Entity is monitoring the effectiveness of the DC processes with pre-defined KPIs. | J44: • The Entity is continuously improving the process for DC. • Innovative solutions and tools are explored to proactively scan and prioritize the classification of Data. | K44: =VLOOKUP(C44, Calculation!$T$3:$AA$45,8,FALSE) -> 2
C45: DC.MQ.3 | D45: Has the Entity reviewed all its classified Datasets and artifacts to ensure that the classification levels assigned to them are the most appropriate ones as specified by the Data Classification (DC) Policies? | E45: No existing Data Classification (DC) review processes are in place. | F45: Existing DC review activities are on a reactive or ad hoc basis. | G45: The Entity defined a review mechanism for all classified Datasets and artifacts to be reviewed. | H45: • The Entity is implementing the defined mechanism for DC reviews for the classified Datasets and artifacts across the Entity. • The Entity is publishing on the Data Catalog the DC levels for the reviewed Datasets and artifacts as Metadata. | I45: The Entity is monitoring the DC review mechanism with pre-defined KPIs. | J45: The Entity is continuously improving its DC review process to ensure optimization. | K45: =VLOOKUP(C45, Calculation!$T$3:$AA$45,8,FALSE) -> 1
B46: Personal Data Protection | C46: PDP.MQ.1 | D46: Has the Entity performed an initial Personal Data Protection (PDP) assessment and developed a plan to address the strategic and operational Privacy requirements? | E46: • No assessment is done for Personal Data Protection (PDP). • No plan is in place to address Data Privacy requirements. | F46: • The Entity is aware of the requirements for Data Privacy Management. • The Entity conducted an initial PDP Assessment to evaluate the current state of the Entity's PDP practices, identified gaps against business and regulatory obligations including the following: 1. Identification of the types of personal data being collected. 2. Location & method of personal data storage. 3. Current processing & uses of the personal data. 4. Privacy challenges to meet compliance with the PDP Regulations published by NDMO-SDAIA. | G46: The Entity developed a plan to address the Strategic and Operational Data-Privacy requirements, including a list of activities, required resources, training courses and a budget. | H46: • The Entity is implementing the defined PDP & Data Privacy program in a formalized manner. • This program includes implementing activities which ensure the proactive identification and resolution of potential Privacy issues and risks including training and awareness for all employees to promote a Personal Data Protection-centric culture. | I46: The Entity is monitoring the effectiveness of the PDP plan with pre-defined Key Performance Indicators (KPIs). | J46: The Entity periodically reviews its PDP plan to ensure sustained compliance with the applicable regulations, and other environmental requirements or impacts. | K46: =VLOOKUP(C46, Calculation!$T$3:$AA$45,8,FALSE) -> 1
C47: PDP.MQ.2 | D47: Has the Entity defined and implemented Privacy policies and processes for Personal Data including Data breach identification, consent management, Data subject rights, and Privacy risk assessments? | E47: No practices are in place to identify and address Data breaches nor Privacy violations. | F47: • The Entity identifies Data breaches or Privacy violations on a reactive basis without standardized practices nor policies. • The Entity addresses violations when ad hoc Data Privacy interventions occur. | G47: • The Entity has developed policies and processes for PDP and Data Privacy including the identification of Data breaches, Data Privacy considerations, privacy notice & consent management, and compliance management to comply with the applicable regulations. • Governance has been defined to manage compliance with the PDP regulations in line with the Data Management Organization structure. • The Entity has defined a process for Data Subjects' rights management. | H47: • The Entity is implementing and standardizing the developed and approved practices for PDP including the Consent Management Workflow, notifications to regulatory authority as required and data breach management. • The PDP policies and standardized processes for data subjects rights have been published on the Entity's official government website with a feedback mechanism for questions or issues raised by the data subjects. • The Entity maintains a register of its compliance records including records of any collection and / or processing of any Personal Data (e.g. Identified Data breaches, etc.). The register is made available to regulators as required. | I47: • The Entity is monitoring The effectiveness of its PDP practices and compliance with The rules & regulations through pre-defined KPIs. • The Entity is conducting periodic audits on compliance with PDP rules & regulations. | J47: • The Entity continuously reviews its PDP practices to ensure sustained compliance with regulations. • Continuous improvement, enabled by automation & change management, is performed in line with the defined regulatory requirements. | K47: =VLOOKUP(C47, Calculation!$T$3:$AA$45,8,FALSE) -> 1

Sheet NDMO Specs. Overview
A1: Domain | B1: ID | C1: Specification | D1: Description | E1: Priority | F1: Compliance Level
A4: Data Governance | B4: DG.1.1 | C4: Data Management and Personal Data Protection Strategy | D4: The Entity shall establish a Data Management and Personal Data Protection Strategy to align Entity data initiatives and relevant stakeholders to achieving its business goals, in alignment with the overall program strategy. The Strategy shall cover all domains and reflect: 1. Current data management challenges 2. Strategic requirements covering internal requirements derived from the Entity's business strategy as well as external requirements derived from the National Data Management Agenda 3. Data Management and Personal Data Protection Vision, Mission and Strategic Goals and Objectives 4. Strategic and Operational performance metrics with targets across the 3 to 5 years strategy duration 5. Required financial budget for the implementation of the strategy, broken down by initiatives. | E4: P1 | F4: =IF(G4="Yes","Fully Compliant",IF(G4="Under Development","Partially Compliant","Non-Compliant")) -> Fully Compliant | G4: =IF(VLOOKUP(B4,Master!$I$5:$L$542, 3, 0)<>0, VLOOKUP(B4,Master!$I$5:$L$542, 3, 0), "") -> Yes
B5: DG.1.2 | C5: Guiding Principles | D5: The Entity shall adopt the National Data Management and Personal Data Protection Program's Guiding Principles to affirm alignment of the Entity's Data Management and Personal Data Protection Strategy to the National Data Management and Personal Data Protection agendas. The Entity may, at its discretion, include additional Entity-level guiding principles to augment the core set of NDMO Guiding Principles. Adoption of the National Data Management and Personal Data Protection Program's Guiding Principles shall be articulated either in the Data Management and Personal Data Protection Strategy or as a standalone document. The guiding principles establish a data-centric culture where all stakeholders are unified in understanding what is most important for the Entity's Data Management and Personal Data Protection agendas. | E5: P1 | F5: =IF(G5="Yes","Fully Compliant",IF(G5="Under Development","Partially Compliant","Non-Compliant")) -> Fully Compliant | G5: =IF(VLOOKUP(B5,Master!$I$5:$L$542, 3, 0)<>0, VLOOKUP(B5,Master!$I$5:$L$542, 3, 0), "") -> Yes
